Workbook

Sheet README
A1: Supplementary material: Trusted Execution for Sensor-Based Health Diagnostics: A Scoping Review and Attestation Appraisal Profile
A2: Reporting guideline: PRISMA-ScR. Searches run in OpenAlex on 2026-10-12 (see 'Search log').
A3: Sheets: Coding rules (element definitions and counting rules); Search log (queries and counts); Criteria (inclusion and exclusion codes, incl. the 2026-10-12 amendment); Screening (all 435 records with decisions); Included studies (charting of the 55 included studies); PRISMA counts (formulas over 'Screening').
A4: MITC elements: D device identity, F firmware/code, A acquisition configuration, C calibration, M model version, N freshness, H(R) reading digest. 1 = the study protects the element as stated in the source; blank = not stated.
A5: Charting source: 'Full text' or 'Abstract only'. Abstract-only coding is provisional and conservative (an element is coded only if the abstract states it).
A6: Screening decisions were suggested by keyword rules and an AI assistant (Claude, Anthropic) and checked by the author.
A7: Evidence levels: studies read in full form the primary synthesis (Tables II-III and the gap findings); abstract-only studies are supplementary evidence with provisional coding ('Evidence level' column).
A8: Screening sheet, Next-to-last column: retrieval outcome for each of the 72 reports sought (full text obtained, or not retrieved and assessed on title and abstract). Included studies sheet: 'Evidence type for coded elements' distinguishes implemented and evaluated protection, design-only proposals, formal-only verification, and demonstrated weaknesses (attacks).

Sheet Coding rules
A1: Element | B1: Coded when the study (read in full for primary studies)... | C1: Not coded when... | D1: Example
A2: D: device identity | B2: binds data or keys to a specific physical device: PUF responses, device keys certified by a manufacturer/PKI, or physical fingerprints used to identify the device | C2: a key exists but is not tied to a device identity (e.g., shared symmetric key) | D2: Gas-sensor PUFs; Yoshida (PUF root of trust); Shams (TEE-generated key + X.509 certificate)
A3: F: firmware or code | B3: a verifier checks measurements of the code that processes readings (remote attestation, measured boot with quote) | C3: secure boot only, with no evidence available to a remote verifier | D3: PAtt (hash of PLC logic); ImageBox (attested SGX classifier); Benlloch-Lopez (TPM quote, design only)
A4: A: acquisition configuration | B4: actual sensor or peripheral configuration registers (not just driver code) are read and checked by a verifier | C4: only firmware containing a driver is attested | D4: ERAMO: BME280 ctrl_hum/ctrl_meas/config and I2C registers checked at attestation time (not per reading; ADC not covered)
A5: C: calibration | B5: calibration parameters, version, or update authorization are protected or bound to results | C5: calibration is only named as a threat | D5: None; Li et al. names calibration deviation as a threat only
A6: M: model version | B6: the model used is bound to the result (identity), or model updates are authorized/versioned | C6: the model is only kept confidential | D6: ImageBox (model identity recorded, no version policy); Benlloch-Lopez (signed, version-controlled updates, design only); SecureQNN excluded (confidentiality only)
A7: N: freshness | B7: each reading or attestation includes a nonce, counter, or timestamp checked by the verifier | C7: timestamps exist but are not protected or checked | D7: PAtt (verifier nonce); Cabrera-Gutierrez (HSM/TEE timestamp); Hu (nonces, formal verification only)
A8: H(R): reading digest | B8: each reading (or batch) is signed, MACed, or hashed so the verifier can detect alteration | C8: data are only encrypted in transit without per-reading integrity at the source | D8: Yoshida, Oyama (PUF-keyed MAC per frame); Shams (TEE-signed readings); Heiss (signed measurements verified in enclave)
A9: Counting rule | B9: A single mechanism can count for two elements only when both conditions are separately met (e.g., a certified device key counts as D; the per-reading signature made with it counts as H(R)).
A10: Evidence types | B10: Implemented and evaluated; Design only (no evaluation); Formal verification only; Weakness shown (attack, not protection); Per abstract (supplementary, provisional). Recorded in the Included studies sheet.
A11: Evidence levels | B11: Primary: charted from full text (used for Table II and the gap findings). Supplementary: charted from abstract only; an element is coded only if the abstract states it, so absence is not evidence of absence.

Sheet Search log
A1: Search ID | B1: Database | C1: Exact query | D1: Date run (YYYY-MM-DD) | E1: Results shown
A2: R1 | B2: OpenAlex (completed) | C2: title-abstract-keywords has (stemmed "confidential computing" AND stemmed "medical IoT") | D2: 2026-10-12 | E2: 1
A3: R2 | B3: OpenAlex (completed) | C3: title-abstract-keywords has (stemmed "breath analysis" AND privacy) | D3: 2026-10-12 | E3: 16
A4: R3 | B4: OpenAlex (completed) | C4: title-abstract-keywords has (authentication AND stemmed "gas sensor") | D4: 2026-10-12 | E4: 71
A5: R4 | B5: OpenAlex (completed) | C5: title-abstract-keywords has (stemmed "electronic nose" AND security) | D5: 2026-10-12 | E5: 182
A6: R5 | B6: OpenAlex (completed) | C6: title-abstract-keywords has (provenance AND stemmed "trusted sensor") | D6: 2026-10-12 | E6: 1
A7: R6 | B7: OpenAlex (completed) | C7: title-abstract-keywords has (stemmed "remote attestation" AND sensor) | D7: 2026-10-12 | E7: 54
A8: R7 | B8: OpenAlex (completed) | C8: title-abstract-keywords has (stemmed "trusted execution environment" AND "sensor") | D8: 2026-10-12 | E8: 84
A9: R8 | B9: OpenAlex (completed) | C9: title-abstract-keywords has ((stemmed "trusted execution environment" OR TrustZone OR SGX OR enclave OR stemmed "remote attestation" OR stemmed "confidential computing" OR stemmed "physically unclonable function") AND (stemmed "electronic nose" OR stemmed "gas sensor" OR stemmed "chemical sensor" OR stemmed "breath analysis" OR "exhaled breath" OR chemiresistive)) | D9: 2026-10-12 | E9: 20

Sheet Criteria
A1: Code | B1: Rule
A2: I1 | B2: Proposes or evaluates a TEE, attestation, PUF/device-identity, or cryptographic mechanism that protects the integrity, authenticity, or confidentiality of sensor or health DATA: the readings, their processing, or results derived from them (including authenticating the origin of readings). Protecting only an ML model does not qualify (clarified 2026-10-17). Narrowed on 2026-10-12, before full-text review.
A3: I2 | B3: Or: applies ML or data handling to chemical-sensor arrays (e-nose, gas, breath) AND addresses security, privacy, integrity, or authentication.
A4: I3 | B4: Peer-reviewed paper or widely cited preprint, published 2012–2026, with an English title and abstract (as applied at screening; one included full text in Chinese was read in translation).
A5: E1 | B5: Off topic: not about the security or trust of sensing or health data (e.g., biology "enclave", sensor chemistry with no security aspect).
A6: E2 | B6: No technical design or evaluation (editorial, news, opinion, abstract only).
A7: E3 | B7: Not in English.
A8: E4 | B8: Duplicate or earlier version of an included paper.
A9: E5 | B9: Full text not available.
A10: E6 | B10: Published outside 2012–2026.
A11: E7 | B11: Not peer-reviewed (thesis, podcast, dataset or code repository, webinar, self-published report).
A12: E8 | B12: Protects device, firmware, or platform state only, not sensor or health DATA (narrower rule of 2026-10-12, applied retrospectively to every record that had passed title/abstract screening). Scope clarified 2026-10-17 to include ML-model-only protection (one further exclusion, S0383). May still be cited as background.
A13: Note | B13: Title/abstract stage: decide Include, Exclude (with code), or Maybe. Maybe goes to full-text review. Full-text stage: Include, or Exclude with code.

Sheet Screening
A1: Record ID | B1: Source | C1: Search ID | D1: Title | E1: Authors | F1: Year | G1: Venue | H1: DOI / ID | I1: Duplicate of (Record ID) | J1: T/A decision | K1: T/A reason | L1: Full-text decision | M1: FT reason | N1: Mechanism | O1: Pipeline stage | P1: Asset protected | Q1: Chemical-sensor data? (Y/N) | R1: Notes | S1: Retrieval outcome (eligibility stage)
A2: R0001 | B2: Other: web check | C2: — | D2: Trusted Operations on Sensor Data | E2: H. Janjua, W. Joosen, S. Michiels, D. Hughes | F2: 2018 | G2: Sensors 18(5), 1364 | H2: 10.3390/s18051364 | J2: Include | L2: Include | N2: TrustZone (OP-TEE) secure operations on sensor data | O2: Acquisition | P2: Secrecy, integrity, freshness of readings | Q2: N | R2: Full text read. Raspberry Pi 3 + BLE pulse sensor; timing overhead only; no calibration or drift. | Pulse sensor and camera on Raspberry Pi 3; no gas sensors; evaluation reports timing, not drift or calibration. | S2: Full text obtained and read
A3: R0002 | B3: Other: web check | C3: — | D3: Gas Sensor Physically Unclonable Function-Based Lightweight Bidirectional Authentication Protocol for Gas Sensor Networks | E3: S. Hu, P. Wang, H. He, Y. Zhang, X. Li | F3: 2024 | G3: Electronics 13(17), 3385 | H3: 10.3390/electronics13173385 | I3: S0026 | J3: Exclude | K3: E4 | N3: Gas-sensor PUF + auth protocol | O3: Device identity | P3: Node authentication | Q3: Y | R3: ZnO-SnO2 sensor array as PUF; >98% reliability over 20 days; not breath, no TEE.
A4: R0003 | B4: Other: web check | C4: — | D4: High Steady-state Physical Unclonable Function Generator Based on Gas Sensors | E4: P. Wang, L. Li, Y. Zheng, G. Li | F4: 2021 | G4: J. Electronics & Information Technology 43(6), 1596–1602 | H4: 10.11999/JEIT201104 | J4: Include | L4: Include | N4: Gas-sensor PUF (Pd-SnO2 nanofibers; 8-sensor array, 3-sensor cluster comparisons, 128-bit response) | O4: Device identity | P4: Node identity | Q4: Y | R4: Full text read (Chinese full text; English title and abstract; JEIT 43(6):1596-1602, 2021). Formaldehyde stimulus; reliability 97.85% tested only across heater voltage 4.2-4.9 V (5 samples) and a 400 s run at room conditions (100% for 90 s, >95% after); humidity and long-term drift not tested. Uniqueness 49.04%; randomness 97.03% in abstract vs 98.06% in text. No authentication protocol, reading or calibration binding. Elements: D. | Pd-SnO2 sensors, formaldehyde; check whether full text is English (E3 if not). | S4: Full text obtained and read
A5: R0004 | B5: Other: web check | C5: — | D5: Fingerprinting Analog IoT Sensors for Secret-Free Authentication | E5: F. Lorenz et al. | F5: 2020 | G5: arXiv preprint | H5: arXiv:2006.06296 | J5: Maybe | L5: Exclude | M5: E7 | N5: Analog sensor fingerprinting (temperature sensors) | O5: Transduction | P5: Sensor authenticity | Q5: N | R5: Full text read. arXiv preprint only. Cite as background for analog trust boundary. | Temperature sensors; relevant to the analog trust boundary. | S5: Full text obtained and read
A6: R0005 | B6: Other: web check | C6: — | D6: This Ain't Your Dose: Sensor Spoofing Attack on Medical Infusion Pump | E6: Y. Park, Y. Son, H. Shin, D. Kim, Y. Kim | F6: 2016 | G6: USENIX WOOT 2016 | H6: woot16-paper-park | J6: Include | L6: Include | N6: Sensor spoofing attack on infusion-pump drop sensor | O6: Transduction | P6: Medical sensor integrity | Q6: N | R6: Full text read. Laser spoofing from ~12 m; over-infusion up to ~3.3x. Physical attack below any TEE. | Physical spoofing of a medical sensor; supports the transduction threat in Table I. | S6: Full text obtained and read
A7: R0006 | B7: Other: web check | C7: — | D7: PDRIMA: A Policy-Driven Runtime Integrity Measurement and Attestation Approach for ARM TrustZone-based TEE | E7: J. Mao, X. Chang | F7: 2025 | G7: arXiv preprint | H7: arXiv:2512.06500 | J7: Exclude | K7: E8 | N7: TrustZone runtime attestation | O7: Device / runtime | P7: TEE runtime integrity | Q7: N | R7: General TrustZone attestation; no sensors. Likely E1 at full text unless used as background.
A8: S0001 | B8: OpenAlex | C8: R1 | D8: Protecting patient confidentiality in the Internet of Medical Things through confidential computing | E8: Richard Searle, Prabhanjan Gururaj | F8: 2023 | H8: https://doi.org/10.69554/ccmf2668 | J8: Include | L8: Exclude | M8: E2 | N8: Conceptual confidential-computing architecture | O8: Analytics | P8: PHI confidentiality | Q8: N | R8: Charted from abstract only. Position paper; no implementation or evaluation. Cite as background. | Confidential computing for IoMT data | S8: Full text not retrieved (paywalled or unavailable); assessed on title and abstract
A9: S0002 | B9: OpenAlex | C9: R2 | D9: Breath analysis using FTIR spectroscopy | E9: Andrei A. Bunaciu, Hassan Youssef Aboul-Enein | F9: 2025 | H9: https://doi.org/10.37349/emed.2025.1001308 | J9: Exclude | K9: E1 | R9: Off topic: sensing or security application without protection of sensor/health data
A10: S0003 | B10: OpenAlex | C10: R2 | D10: The AI Nose Knows: Digital Olfaction and Emotional Scent | E10: Rocky Scopelliti | F10: 2026 | H10: https://doi.org/10.1201/9781003737063-12 | J10: Exclude | K10: E1 | R10: Off topic: sensing or security application without protection of sensor/health data
A11: S0004 | B11: OpenAlex | C11: R2 | D11: The digitization of health care retailing | E11: Mark Scott Rosenbaum, Germán Contreras Ramírez, Karen Edwards, Ji-Yeon Kim, J Campbell, Marianne C. Bickle | F11: 2017 | H11: https://doi.org/10.1108/jrim-07-2017-0058 | J11: Exclude | K11: E1 | R11: Off topic: sensing or security application without protection of sensor/health data
A12: S0005 | B12: OpenAlex | C12: R2 | D12: Artificial Intelligence for Noninvasive Health Diagnostics | E12: Pushkar Wankhede, Devendra Bhuyar, Shrinivas R. Zanwar, Rohit Pawar, Mahendra R. Jadhav, Nisarg Gandhewar, Madhusudan B. Kulkarni, Manish L. Bhaiyya, Hossam Haick | F12: 2025 | H12: https://doi.org/10.1021/acssensors.5c03171 | J12: Exclude | K12: E1 | R12: Off topic: sensing or security application without protection of sensor/health data
A13: S0006 | B13: OpenAlex | C13: R2 | D13: AI-Integrated biosensors: A paradigm shift in multi-cancer detection with enhanced sensitivity and specificity | E13: Fatima Naseer, Ufra Naseer, Muhammad Yousaf, Junnan Wei, Yuxuan Gao, Dan Li, Xiujia Tian, Yanqing Liu, Xueyan Li, Fang Wang, Ping Luo | F13: 2026 | H13: https://doi.org/10.1016/j.snr.2026.100439 | J13: Exclude | K13: E1 | R13: Off topic: sensing or security application without protection of sensor/health data
A14: S0007 | B14: OpenAlex | C14: R2 | D14: Breath as a biomarker: A survey of contact and contactless applications and approaches in respiratory monitoring | E14: A.L.M.U.S.T.A.P.H.A.A. WAKILI, Babajide J. Asaju, Woosub Jung | F14: 2025 | H14: https://doi.org/10.1016/j.smhl.2025.100579 | J14: Exclude | K14: E1 | R14: Off topic: sensing or security application without protection of sensor/health data
A15: S0008 | B15: OpenAlex | C15: R2 | D15: A Review and Performance Study of AI Techniques in Asthma Prediction | E15: Dr Prashant Kumar Srivastava | F15: 2026 | J15: Exclude | K15: E1 | R15: Off topic: sensing or security application without protection of sensor/health data
A16: S0009 | B16: OpenAlex | C16: R2 | D16: Synthetic Exhaled Breath Data-Based Edge AI Model for the Prediction of Chronic Obstructive Pulmonary Disease | E16: Samson Otieno Ooko, Didacienne Mukanyiligira, Jean Pierre Munyampundu, Jimmy Nsenga | F16: 2021 | H16: https://doi.org/10.1109/i3cat53310.2021.9629420 | J16: Exclude | K16: E1 | R16: Off topic: sensing or security application without protection of sensor/health data
A17: S0010 | B17: OpenAlex | C17: R2 | D17: Impaction-based exhaled breath sampling for substance monitoring: a prospective pilot study (Drugxhale) | E17: Lutea A. A. de Jong, Erik J. H. Olyslager, Jan A Wieferink, Maarten Keizer, Tobias Cornielje, Robbert Peter Zuidema | F17: 2024 | H17: https://doi.org/10.1088/1752-7163/ad80b6 | J17: Exclude | K17: E1 | R17: Off topic: sensing or security application without protection of sensor/health data
A18: S0011 | B18: OpenAlex | C18: R2 | D18: Capture and analysis of amphetamine-like stimulants in exhaled breath using functionalized cotton fibers | E18: Zirun Ren, Litao Shao, Yudi Zhang, Bin Di, Mengxiang Su | F18: 2026 | H18: https://doi.org/10.1016/j.microc.2026.119098 | J18: Exclude | K18: E1 | R18: Off topic: sensing or security application without protection of sensor/health data
A19: S0012 | B19: OpenAlex | C19: R2 | D19: Disposable Face Masks for Noninvasive Drug Detection: A Proof-of-Concept Study with Cough Syrup Constituents | E19: Hei-Tak Tse, Jian Zhen Yu, Zongwei Cai, Wan Chan | F19: 2025 | H19: https://doi.org/10.1021/acs.analchem.5c01129 | J19: Exclude | K19: E1 | R19: Off topic: sensing or security application without protection of sensor/health data
A20: S0013 | B20: OpenAlex | C20: R2 | D20: Capture and Analysis of Amphetamine-like Stimulants in Exhaled Breath Using Functionalized Cotton Fibers | E20: Zirun Ren, Litao Shao, Yudi Zhang, Bin Di, Mengxiang Su | F20: 2026 | H20: https://doi.org/10.2139/ssrn.6869062 | I20: S0011 | J20: Exclude | K20: E4 | R20: AI-suggested, confirm. Duplicate
A21: S0014 | B21: OpenAlex | C21: R2 | D21: Tiny Machine Learning (TinyML) Based Self Diagnostic Kit for Respiratory Diseases | E21: Samson Otieno Ooko, Jimmy Nsenga | F21: 2023 | H21: https://doi.org/10.1109/icca59364.2023.10401673 | J21: Exclude | K21: E1 | R21: Off topic: sensing or security application without protection of sensor/health data
A22: S0015 | B22: OpenAlex | C22: R2 | D22: State-of-the-art TinyML approaches for colorectal cancer detection: Current advances, challenges, and future directions | E22: Showkat Ahmad Bhat, Ming-Che Chen, Nen-Fu Huang | F22: 2026 | H22: https://doi.org/10.1016/j.artmed.2026.103481 | J22: Exclude | K22: E1 | R22: Off topic: sensing or security application without protection of sensor/health data
A23: S0016 | B23: OpenAlex | C23: R2 | D23: Public Preferences for Emerging Cancer Screening Modalities: A Systematic Review of Discrete Choice Experiments | E23: Chee Ern Har, Qi Gao, Wenjia Chen, Yi Wang | F23: 2025 | H23: https://doi.org/10.1007/s40271-025-00775-1 | J23: Exclude | K23: E1 | R23: Off topic: sensing or security application without protection of sensor/health data
A24: S0017 | B24: OpenAlex | C24: R2 | D24: ONCO-VOC AI module | E24: Ioannis Gallos | F24: 2026 | H24: https://doi.org/10.5281/zenodo.19203817 | J24: Exclude | K24: E7 | R24: AI-suggested, confirm. Not peer-reviewed (thesis, podcast, dataset, repository, webinar)
A25: S0018 | B25: OpenAlex | C25: R3 | D25: Detection of Authentication of Milk by Nanostructure Conducting Polypyrrole-ZnO | E25: Sajad Pirsa, Şeref Tağı, Mohammad Rezaei | F25: 2021 | H25: https://doi.org/10.1007/s11664-021-08855-2 | J25: Exclude | K25: E1 | R25: Off topic: sensing or security application without protection of sensor/health data
A26: S0019 | B26: OpenAlex | C26: R3 | D26: Housing Society Management, Authentication and Security App | E26: Durga Bhavani.A | F26: 2017 | H26: https://doi.org/10.18535/ijecs/v6i6.05 | J26: Exclude | K26: E1 | R26: Off topic: sensing or security application without protection of sensor/health data
A27: S0020 | B27: OpenAlex | C27: R3 | D27: Human Body Odor Based Authentication Using Machine Learning | E27: Yang Bin, Wonjun Lee | F27: 2018 | H27: https://doi.org/10.1109/ssci.2018.8628697 | J27: Maybe | L27: Include | N27: Gas-sensor odor biometric + ML (K-means, PCA, NN) | O27: Inference | P27: Person identity (I2) | Q27: Y | R27: Full text read (IEEE SSCI 2018). Body-odor samples from MQ-series gas sensors; K-means, PCA and neural network identify individuals with high accuracy. Shows odor data are identifying (I2). No protection mechanism. No elements coded. | Odor biometric | S27: Full text obtained and read
A28: S0021 | B28: OpenAlex | C28: R3 | D28: Design and Implementation of Industrial security system using Fingerprint Authentication and IOT | E28: Ch. Narasimha Rao, M. Rambabu | F28: 2018 | J28: Exclude | K28: E1 | R28: Off topic: sensing or security application without protection of sensor/health data
A29: S0022 | B29: OpenAlex | C29: R3 | D29: CBC (Cipher Block Chaining)-Based Authenticated Encryption for Securing Sensor Data in Smart Home | E29: S Rajashree, Rajkumar Sukumar | F29: 2021 | H29: https://doi.org/10.1007/978-3-030-71485-7_12 | J29: Include | L29: Include | N29: AES-128-CBC encryption with CBC-MAC for sensor data before transmission | O29: Transmission | P29: Confidentiality and integrity of sensor data in transit | Q29: N | R29: Full text read (Springer/EAI chapter, 2021). ESP32 with DHT11 temperature-humidity sensor; timestamped readings written to a file and encrypted with AES-CBC, last block used as MAC. Gas sensors mentioned only as a possible addition, so no chemical-sensor data were used (reclassified from Y). No performance evaluation, device-side protection, freshness, attestation, calibration or model binding. No elements coded. | Authenticated encryption of smart-home sensor data | S29: Full text obtained and read
A30: S0023 | B30: OpenAlex | C30: R3 | D30: Automated Detection of Porcine Gelatin Using Deep Learning-Based E-Nose to Support Halal Authentication | E30: Kunti Robiatul Mahmudah, Muhammad Kunta Biddinika, Dhias Cahya Hakika, Wildan Panji Tresna, Iyon Titok Sugiarto, Inna Syafarina | F30: 2025 | H30: https://doi.org/10.35882/jeeemi.v7i1.654 | J30: Exclude | K30: E1 | R30: Off topic: sensing or security application without protection of sensor/health data
A31: S0024 | B31: OpenAlex | C31: R3 | D31: Odor-based individual authentication | E31: Wataru Tanaka, Chaiyanut Jirayupat, Haruka Honda, Jiangyang Liu, Takuro Hosomi, Tsunaki Takahashi, Takeshi Yanagida | F31: 2025 | H31: https://doi.org/10.1039/d5cc02465j | J31: Maybe | L31: Exclude | M31: E2 | N31: Review of odor-based authentication (skin, breath) | O31: — | P31: — | Q31: Y | R31: Charted from abstract only. Review without own evaluation; cite as background for breath re-identification risk. | Odor biometric | S31: Full text not retrieved (paywalled or unavailable); assessed on title and abstract
A32: S0025 | B32: OpenAlex | C32: R3 | D32: Authentication and adulteration detection of true cinnamon (Cinnamomum zeylanicum) essential oil using an integrated multi-analytical and electronic nose approach | E32: Giovana Feltes, Ilizandra Aparecida Fernandes, Juliana Steffens, Natália Paroul, Clarice Steffens | F32: 2026 | H32: https://doi.org/10.1016/j.compag.2026.111825 | J32: Exclude | K32: E1 | R32: Off topic: sensing or security application without protection of sensor/health data
A33: S0026 | B33: OpenAlex | C33: R3 | D33: Gas Sensor Physically Unclonable Function-Based Lightweight Bidirectional Authentication Protocol for Gas Sensor Networks | E33: Shuang Hu, Pengjun Wang, Haonan He, Yuejun Zhang, Xiangyu Li | F33: 2024 | H33: https://doi.org/10.3390/electronics13173385 | J33: Include | L33: Include | N33: Gas-sensor PUF (ZnO-SnO2 array) + lightweight bidirectional user-server-node authentication protocol (hash, XOR, nonces), ProVerif-verified | O33: Device identity / transmission | P33: Node authentication; session key for transmitting gas data | Q33: Y | R33: Full text read (Electronics 2024, 13(17), 3385). D: GS-PUF response hashed for node authentication; ethanol and methanol stimuli. N: user and server random numbers per session; formally resists replay, impersonation, node tampering and cloning (ProVerif only, no hardware protocol timing). Gas data sent under a session key (confidentiality), but individual readings are not digested or signed. No calibration, firmware or model binding. Elements: D, N. | Gas-sensor PUF authentication protocol | S33: Full text obtained and read
A34: S0027 | B34: OpenAlex | C34: R3 | D34: Identification authentication scheme using human body odour | E34: Minglei Shu, Yunxiang Liu, Hua Fang | F34: 2014 | H34: https://doi.org/10.1109/ccsse.2014.7224531 | J34: Maybe | L34: Exclude | M34: E2 | N34: Odor identification scheme (gas sensor arrays) | O34: — | P34: — | Q34: Y | R34: Charted from abstract only. Theoretical analysis only, no experiments. | Odor biometric | S34: Full text not retrieved (paywalled or unavailable); assessed on title and abstract
A35: S0028 | B35: OpenAlex | C35: R3 | D35: Data processing approaches and strategies for non-destructive fruits quality inspection and authentication: a review | E35: Satyam Srivastava, Shashikant Sadistap | F35: 2018 | H35: https://doi.org/10.1007/s11694-018-9893-2 | J35: Exclude | K35: E1 | R35: Off topic: sensing or security application without protection of sensor/health data
A36: S0029 | B36: OpenAlex | C36: R3 | D36: Design of Gas Sensors-Based PUF for Internet of Things Security | E36: Xiaowei Zhang, Zexin Ji, Xiangyu Li, Pengjun Wang, Yangong Zheng, Shanshan Wang | F36: 2025 | H36: https://doi.org/10.1109/jsen.2025.3540015 | J36: Include | L36: Include | N36: Gas-sensor PUF (TiO2-ZnO nanofibers; 128-bit) | O36: Device identity | P36: Node identity and key management | Q36: Y | R36: Full text read (IEEE Sensors J. 25(7), 2025). Eight TiO2-ZnO sensors, three per cluster, median averaging filter + multi-bit balancing, 128-bit response; varied gas concentrations and operating voltages; uniqueness 49.6%, randomness 98.6%, reliability 97%. Authentication and key management claimed as applications only, no protocol. Humidity not tested. Elements: D. | Gas-sensor PUF (IEEE Sensors J. 2025) | S36: Full text obtained and read
A37: S0030 | B37: OpenAlex | C37: R3 | D37: NASICON-based gas sensor utilizing MMnO3 (M: Gd, Sm, La) sensing electrode for triethylamine detection | E37: Yueying Zhang, Ce Ma, Xinyu Yang, Yang Song, Xishuang Liang, Xu Zhao, Yilin Wang, Yuan Lou Gao, Fengmin Liu, Fangmeng Liu, Peng Sun, Geyu Lu | F37: 2019 | H37: https://doi.org/10.1016/j.snb.2019.05.062 | J37: Exclude | K37: E1 | R37: Off topic: sensing or security application without protection of sensor/health data
A38: S0031 | B38: OpenAlex | C38: R3 | D38: Metal Oxide Semiconductor Gas Sensors-based E-nose and Two-stage Classification: Authentication of Malaysia and Vietnam Black Pepper Samples | E38: Hui En Lee, Zehnder Jarroop Augustine Mercer, Sing Muk Ng, Mahnaz Shafiei, Hong Siang Chua | F38: 2022 | H38: https://doi.org/10.1109/isoen54820.2022.9789618 | J38: Exclude | K38: E1 | R38: Off topic: sensing or security application without protection of sensor/health data
A39: S0032 | B39: OpenAlex | C39: R3 | D39: Potential application of electronic nose coupled with chemometric tools for authentication assessment in tomato paste | E39: Ayat Mohammad‐Razdari, Mahdi Ghasemi‐Varnamkhasti, Seyedeh Hoda Yoosefian, Zahra Izadi, Maryam Siadat | F39: 2019 | H39: https://doi.org/10.1111/jfpe.13119 | J39: Exclude | K39: E1 | R39: Off topic: sensing or security application without protection of sensor/health data
A40: S0033 | B40: OpenAlex | C40: R3 | D40: Rapid analysis of meat floss origin using a supervised machine learning-based electronic nose towards food authentication | E40: Linda Ardita Putri, Iman Rahman, Mayumi Puspita, Shidiq Nur Hidayat, Agus Budi Dharmawan, Aditya Rianjanu, Sunu Wibirama, Roto Roto, Kuwat Trıyana, Hutomo Suryo Wasisto | F40: 2023 | H40: https://doi.org/10.1038/s41538-023-00205-2 | J40: Exclude | K40: E1 | R40: Off topic: sensing or security application without protection of sensor/health data
A41: S0034 | B41: OpenAlex | C41: R3 | D41: Microstructural and morphological insight of wide band gap SnO2 towards gas sensor applications | E41: Jegannathan Mangaiyarkkarasi, V. Meenakumari, N. Thenmozhi | F41: 2023 | H41: https://doi.org/10.1007/s12046-023-02138-8 | J41: Exclude | K41: E1 | R41: Off topic: sensing or security application without protection of sensor/health data
A42: S0035 | B42: OpenAlex | C42: R3 | D42: Multi Level Bank Locker Security System with Digital Signature Authentication and Internet of Things | E42: Md. Ashiqul Islam, Md. Sumon Sarder, Mehedi Hasan Mamun, Faruq Ahmed, Sujit Kumar Sarkar, Aunik Hasan Mridul, Md. Tanvir Ahmed, Tania Khatun | F42: 2022 | H42: https://doi.org/10.21203/rs.3.rs-2173423/v1 | J42: Exclude | K42: E1 | R42: Off topic: sensing or security application without protection of sensor/health data
A43: S0036 | B43: OpenAlex | C43: R3 | D43: Electronic noses and tongues | E43: Ambra Rita Di Rosa, Francesco Leone, Vincenzo Chiofalo | F43: 2020 | H43: https://doi.org/10.1016/b978-0-12-813266-1.00007-3 | J43: Exclude | K43: E1 | R43: Off topic: sensing or security application without protection of sensor/health data
A44: S0037 | B44: OpenAlex | C44: R3 | D44: Application of Electronic Nose Systems on Animal-Source Food | E44: Ambra Rita Di Rosa, Francesco Leone | F44: 2018 | H44: https://doi.org/10.4018/978-1-5225-3862-2.ch008 | J44: Exclude | K44: E1 | R44: Off topic: sensing or security application without protection of sensor/health data
A45: S0038 | B45: OpenAlex | C45: R3 | D45: Analytical equations based prediction approach for PM2.5 using artificial neural network | E45: Jalpa Shah, Biswajit Mishra | F45: 2020 | H45: https://doi.org/10.1007/s42452-020-03294-w | J45: Exclude | K45: E1 | R45: Off topic: sensing or security application without protection of sensor/health data
A46: S0039 | B46: OpenAlex | C46: R3 | D46: A Secret Key Updating Method between Devices for Secure Smart Services | E46: Jin‐Hee Han, Geonwoo Kim | F46: 2018 | H46: https://doi.org/10.1109/ictc.2018.8539417 | J46: Exclude | K46: E8 | R46: Narrower rule: protects device/firmware/platform state only, not sensor or health data (may still be cited as background). Key update for smart services
A47: S0040 | B47: OpenAlex | C47: R3 | D47: Development of a Raspberry Pi-Based IoT Smart Laboratory Trainer with an I2C Display and Solenoid Lock Actuator for the Telecommunications Laboratory of the Faculty of Engineering, UNESA | E47: Ali Mustain, Genta Garuda Bimasakti, Hikmat Oka Kusuma | F47: 2026 | H47: https://doi.org/10.9734/jerr/2026/v28i71966 | J47: Exclude | K47: E1 | R47: Off topic: sensing or security application without protection of sensor/health data
A48: S0041 | B48: OpenAlex | C48: R3 | D48: Molybdenum Carbide MXenes as Efficient Nanosensors toward Selected Chemical Warfare Agents | E48: Puspamitra Panigrahi, Yash Pal, Thanayut Kaewmaraya, Hyeonhu Bae, Noushin Nasiri, Tanveer Hussain | F48: 2023 | H48: https://doi.org/10.1021/acsanm.3c00686 | J48: Exclude | K48: E1 | R48: Off topic: sensing or security application without protection of sensor/health data
A49: S0042 | B49: OpenAlex | C49: R3 | D49: A Secured Distributed IoT Framework for Real-Time Wildfire Detection using Edge Computing and Spatial-Temporal Correlation | E49: Jaswanth Kumar N, N H Shrinandh, Jayasree M. Oli, Paramasivam C. | F49: 2026 | H49: https://doi.org/10.1109/icoei68323.2026.11541877 | J49: Maybe | L49: Include | N49: ECDSA P-256 message authentication + multi-node consensus (ESP32, MQ gas sensors) | O49: Transmission | P49: Authenticity/integrity of gas readings | Q49: Y | R49: Charted from abstract only (abstract supplied by author). Wildfire detection; signing at a Python gateway; consensus of 2+ nodes within 500 m. No TEE. | Secured sensor framework | S49: Full text not retrieved (paywalled or unavailable); assessed on title and abstract
A50: S0043 | B50: OpenAlex | C50: R3 | D50: Experimental performance evaluation of non-toxic metal oxide synthesized via solid-state reaction for room temperature-sensing applications | E50: R. Binowesley, Kirubaveni Savarimuthu, Radha Shankararajan, Iyappan Gunasekaran | F50: 2023 | H50: https://doi.org/10.1007/s12034-023-02988-2 | J50: Exclude | K50: E1 | R50: Off topic: sensing or security application without protection of sensor/health data
A51: S0044 | B51: OpenAlex | C51: R3 | D51: Classification of Alcoholic Beverage Using Electronic Nose and Support Vector Machine | E51: Jon Dave V. Bautista, Marc Julian M. Elizarde, Meo Vincent C. Caya | F51: 2025 | H51: https://doi.org/10.1109/iccae64891.2025.10980518 | J51: Exclude | K51: E1 | R51: Off topic: sensing or security application without protection of sensor/health data
A52: S0045 | B52: OpenAlex | C52: R3 | D52: Integrated Security Home Automation Based on IOT | E52: Prof. V.Srikanth, H Suchetha, K Pravllika | F52: 2018 | H52: https://doi.org/10.14419/ijet.v7i2.32.15710 | J52: Exclude | K52: E1 | R52: Off topic: sensing or security application without protection of sensor/health data
A53: S0046 | B53: OpenAlex | C53: R3 | D53: Crptography based Lifi for Patient Privacy and Emergency Health Service Using IOT | E53: V. T. Vithya, M. P. Chandrasekar, M. Suganthy, J. Jasmine Hephzipah, B. Sarala, Nuthakki Praveena, M. Perarasi | F53: 2022 | H53: https://doi.org/10.17762/ijritcc.v10i2s.5928 | J53: Maybe | L53: Include | N53: SHA hashing for LiFi health IoT data | O53: Transmission | P53: Patient vital-sign data | Q53: Y | R53: Charted from abstract only. Vital-sign kit includes a gas sensor (not breath). Low technical depth. | Crypto for health IoT; low technical depth? | S53: Full text not retrieved (paywalled or unavailable); assessed on title and abstract
A54: S0047 | B54: OpenAlex | C54: R3 | D54: Suitability of chlorobenzene-based single-electron transistor as HCN, AsH3, and COCl2 sensor | E54: Ravi Mehla, Kumar Gaurav, Anurag Srivastava, Sukhbir Singh | F54: 2022 | H54: https://doi.org/10.1007/s00894-022-05195-8 | J54: Exclude | K54: E1 | R54: Off topic: sensing or security application without protection of sensor/health data
A55: S0048 | B55: OpenAlex | C55: R3 | D55: Design of Unmanned All-Terrain Spy Bot | E55: Aditya S Kumar, Aradhana, Shristi Kumari, Shipra Shipra, Deepak Prasad, Divya Sharma, T. Snehitha Reddy, Bhagwan Singh, Deepika Kotwar, Vijay Nath | F55: 2022 | H55: https://doi.org/10.1007/978-981-19-1906-0_30 | J55: Exclude | K55: E1 | R55: Off topic: sensing or security application without protection of sensor/health data
A56: S0049 | B56: OpenAlex | C56: R3 | D56: Classification of Dark Condiment Sauces Through Electronic Nose Using Support Vector Machine | E56: Jose Julian L. Acot, Cherry Ben Jr. R. Bendol, John Paul T. Cruz | F56: 2026 | H56: https://doi.org/10.3390/engproc2026134022 | J56: Exclude | K56: E1 | R56: Off topic: sensing or security application without protection of sensor/health data
A57: S0050 | B57: OpenAlex | C57: R3 | D57: Potentiallity of Surface Modified TiO2 Nanoflowers for Alcohol Sensing Application | E57: Indranil Maity, Partha Bhattacharyya | F57: 2019 | H57: https://doi.org/10.1109/isdcs.2019.8719089 | J57: Exclude | K57: E1 | R57: Off topic: sensing or security application without protection of sensor/health data
A58: S0051 | B58: OpenAlex | C58: R3 | D58: Design of High-Performance Gas-Sensing PUF Based on Nanoparticles/Fibers With Composite Morphology | E58: Haitao Mei, Yuejun Zhang, Haonan He, Yangong Zheng | F58: 2023 | H58: https://doi.org/10.1109/jsen.2023.3312323 | J58: Include | L58: Include | N58: Gas-sensor PUF (EHD nano-SnO2 particle/fiber) + PUF-based gas discrimination scheme | O58: Device identity | P58: Sensor identity; gas discrimination from per-gas PUF difference | Q58: Y | R58: Full text read (IEEE Sensors J. 23(20), 2023). EHD nano-SnO2 particle/fiber sensors; ethanol and formaldehyde at different temperatures; reliability 99.21%, uniqueness 49.37%, NIST pass. Gas authentication scheme distinguishes two reducing gases by PUF-response difference (min HD 57.1% between gases vs max 3.9% across 4.5-4.7 V): a selectivity aid, not authentication of samples or readings. Humidity not tested. Elements: D. | Gas-sensing PUF (IEEE Sensors J. 2023) | S58: Full text obtained and read
A59: S0052 | B59: OpenAlex | C59: R3 | D59: Smart Food Waste Rescue Hub Application: IOT-Enabled Platform for Surplus Food Redistribution | E59: B. Aysha Banu, Sujan Balan S, Sathak Irfan A J, Syed Salman V, Devika S.T. | F59: 2026 | H59: https://doi.org/10.55041/ijsmt.v2i5.132 | J59: Exclude | K59: E1 | R59: Off topic: sensing or security application without protection of sensor/health data
A60: S0053 | B60: OpenAlex | C60: R3 | D60: Computational Investigation of Hafnium Carbide MXenes (Hf 3 C 2 T x ) for Ultra-Sensitive Detection of Targeted Volatile Organic Compounds | E60: Puspamitra Panigrahi, Yash Pal, Hyeonhu Bae, Muhaymin Khan, Hoonkyung Lee, Arifa M. Khan, Tanveer Hussain | F60: 2025 | H60: https://doi.org/10.1021/acs.langmuir.5c03298 | J60: Exclude | K60: E1 | R60: Off topic: sensing or security application without protection of sensor/health data
A61: S0054 | B61: OpenAlex | C61: R3 | D61: Molybdenum Carbide MXenes as Efficient Nanosensors Towards Selected Chemical Warfare Agents | E61: Puspamitra Panigrahi, Pal, Yash, Thanayut Kaewmaraya, Hyeonhu Bae, Noushin Nasiri, Tanveer Hussain | F61: 2023 | H61: https://doi.org/10.48550/arxiv.2302.03181 | J61: Exclude | K61: E1 | R61: Off topic: sensing or security application without protection of sensor/health data
A62: S0055 | B62: OpenAlex | C62: R3 | D62: Implementation of Integrity of Voice and Face Recognition for Home Security by Using GSM and ZIGBEE | E62: Chandrasekhar Lokanadham, B. Purna V. Subbarao, V. Santhisri | F62: 2012 | J62: Exclude | K62: E1 | R62: Off topic: sensing or security application without protection of sensor/health data
A63: S0056 | B63: OpenAlex | C63: R3 | D63: Design of PUF based on a Cr2O3-SnO2 gas sensor for Internet of Things security | E63: Xiali Han, Shanshan Wang, Jianding Yu, Pengjun Wang, Xiangyu Li | F63: 2026 | H63: https://doi.org/10.1016/j.measurement.2026.121395 | J63: Include | L63: Include | N63: Gas-sensor PUF (Cr2O3-SnO2; block-mapped random projection; 128-bit) | O63: Device identity | P63: Node identity and key management | Q63: Y | R63: Charted from abstract only (full text unavailable). Uniqueness 50.02%, randomness 98.83%, reliability 97.21%; ML modeling attacks near 0.5 accuracy for 8 models; resistant to environmental disturbance (per abstract). No data binding, TEE, or health use stated. | Gas-sensor PUF (Measurement 2026) | S63: Full text not retrieved (paywalled or unavailable); assessed on title and abstract
A64: S0057 | B64: OpenAlex | C64: R3 | D64: Analytical determination of load resistance value for MQ-series gas sensors: MQ-6 as case study | E64: A. T. Ajiboye, Jayeola Femi Opadiji, Abdulrahman Olalekan Yusuf, Jacob Olagbenro Popoola | F64: 2021 | H64: https://doi.org/10.12928/telkomnika.v19i2.17427 | J64: Exclude | K64: E1 | R64: Off topic: sensing or security application without protection of sensor/health data
A65: S0058 | B65: OpenAlex | C65: R3 | D65: Fraud detection of black pepper using metal oxide semiconductor gas sensors | E65: Hui En Lee, Hong Siang Chua, Zehnder Jarroop Augustine Mercer, Sing Muk Ng, Mahnaz Shafiei | F65: 2021 | H65: https://doi.org/10.1109/sensors47087.2021.9639658 | J65: Exclude | K65: E1 | R65: Off topic: sensing or security application without protection of sensor/health data
A66: S0059 | B66: OpenAlex | C66: R3 | D66: Nebulized spray pyrolysis deposited CdO thin films for liquefied petroleum gas and ethanol gas sensor | E66: V. Vijayanarayanan, V. Aravindan, Karuppasamy Balasubramanian | F66: 2024 | H66: https://doi.org/10.1088/1402-4896/ad623f | J66: Exclude | K66: E1 | R66: Off topic: sensing or security application without protection of sensor/health data
A67: S0060 | B67: OpenAlex | C67: R3 | D67: Surface Potential-Based Approach to Estimate Bias Dependent Sensitivity of 1-D Metal Oxide Resistive Gas Sensors | E67: Arnab Hazra | F67: 2020 | H67: https://doi.org/10.1109/jsen.2020.2974960 | J67: Exclude | K67: E1 | R67: Off topic: sensing or security application without protection of sensor/health data
A68: S0061 | B68: OpenAlex | C68: R3 | D68: Microcontroller and Sensor Based Smart Biking System for Driver’s Safety | E68: S. J. Swathi, Shubham Raj, D. Devaraj | F68: 2019 | H68: https://doi.org/10.1109/incos45849.2019.8951409 | J68: Exclude | K68: E1 | R68: Off topic: sensing or security application without protection of sensor/health data
A69: S0062 | B69: OpenAlex | C69: R3 | D69: Energy-Optimized IoT Smart Home with Biometric Security and Real-Time Environmental Monitoring | E69: Md. Akash Hosen, Md. Farukuzzaman Khan, Md. Robiul Hoque | F69: 2025 | H69: https://doi.org/10.1109/raaicon69033.2025.11502309 | J69: Exclude | K69: E1 | R69: Off topic: sensing or security application without protection of sensor/health data
A70: S0063 | B70: OpenAlex | C70: R3 | D70: Temporal Gated Neural Model for Odor Classification in TinyML Devices | E70: Jihad Rahmawan, Anton Yudhana, Julia Mega Risky | F70: 2025 | H70: https://doi.org/10.1109/icoait67446.2025.11308749 | J70: Exclude | K70: E1 | R70: Off topic: sensing or security application without protection of sensor/health data
A71: S0064 | B71: OpenAlex | C71: R3 | D71: Electronic Nose-Driven Classification of Sri Lankan Teas: An Ensemble Learning Approach Based on Aroma Profiles | E71: Bhashitha Kaveesh, Thosini Kumarika, Dakshika Wanniarachchi, Tharaga Sharmilan | F71: 2026 | H71: https://doi.org/10.1109/scse70081.2026.11499810 | J71: Exclude | K71: E1 | R71: Off topic: sensing or security application without protection of sensor/health data
A72: S0065 | B72: OpenAlex | C72: R3 | D72: Raspberry Pi-Based Carbon Footprint Analyzer for Smart Homes | E72: Rayapaneni Mourya Vardhan, Batchu Jahnavi, P. V. Vidya Varshini, Syed Vaheeda, Dasari Narendra | F72: 2026 | H72: https://doi.org/10.55041/ijsrem59057 | J72: Exclude | K72: E1 | R72: Off topic: sensing or security application without protection of sensor/health data
A73: S0066 | B73: OpenAlex | C73: R3 | D73: Development of Electronic Nose with Low-Cost Dynamic Headspace for Classifying Vegetable Oils and Animal Fats | E73: Kuwat Trıyana, M. Taukhid Subekti, Prasetyo Aji, Shidiq Nur Hidayat, Abdul Rohman | F73: 2015 | H73: https://doi.org/10.4028/www.scientific.net/amm.771.50 | J73: Exclude | K73: E1 | R73: Off topic: sensing or security application without protection of sensor/health data
A74: S0067 | B74: OpenAlex | C74: R3 | D74: Smart Room Automation System | E74: Siddhartha Srivastava, V Arvind, Rajarshi Mukhopadhyay, Priya B. K | F74: 2026 | H74: https://doi.org/10.1109/ic-icns68863.2026.11537467 | J74: Exclude | K74: E1 | R74: Off topic: sensing or security application without protection of sensor/health data
A75: S0068 | B75: OpenAlex | C75: R3 | D75: Development of a Smart Sensor Array for Adulteration Detection in Black Pepper Seeds using Machine Learning | E75: Sowmya Natarajan, Vijayakumar Ponnusamy | F75: 2023 | H75: https://doi.org/10.14569/ijacsa.2023.0140375 | J75: Exclude | K75: E1 | R75: Off topic: sensing or security application without protection of sensor/health data
A76: S0069 | B76: OpenAlex | C76: R3 | D76: A secure and energy-efficient edge computing improved SZ 2.1 hybrid algorithm for handling iot data stream | E76: Sanjay Patidar, Rajni Jindal, Neetesh Kumar | F76: 2024 | H76: https://doi.org/10.1007/s11042-024-18765-0 | J76: Maybe | L76: Include | N76: Error-bounded SZ 2.1 lossy compression + ChaCha20-Poly1305 authenticated encryption at the edge | O76: Transmission | P76: Confidentiality, integrity and authentication of IoT data streams in transit | Q76: N | R76: Full text read (Multimed. Tools Appl., 2024). Raspberry Pi client; datasets: driver stress (ECG, HR, GSR, RR) and UCI gas sensors for home activity monitoring, but only the temperature readings of the gas dataset were used, so no chemical-sensor data (reclassified from Y). Per-message Poly1305 MAC with 128-bit nonce; reports energy and processing-time reductions. No device-side protection, attestation, calibration or model binding. No elements coded. | Secure IoT data stream | S76: Full text obtained and read
A77: S0070 | B77: OpenAlex | C77: R3 | D77: Design and Validation of a Portable Machine Learning-Based Electronic Nose | E77: Yixu Huang, Iyll‐Joon Doh, Euiwon Bae | F77: 2021 | H77: https://doi.org/10.3390/s21113923 | J77: Exclude | K77: E1 | R77: Off topic: sensing or security application without protection of sensor/health data
A78: S0071 | B78: OpenAlex | C78: R3 | D78: Design of smart automated cooker_a survey and feasibility study | E78: Kavita Sharma, S. R. N. Reddy | F78: 2024 | H78: https://doi.org/10.1007/s11042-024-19764-x | J78: Exclude | K78: E1 | R78: Off topic: sensing or security application without protection of sensor/health data
A79: S0072 | B79: OpenAlex | C79: R3 | D79: Identification and Visualization of Hazardous Gases Using IoT | E79: Yashvin Munsadwala, Pankti Joshi, Pranav R. Patel, Keyur Rana | F79: 2019 | H79: https://doi.org/10.1109/iot-siu.2019.8777481 | J79: Exclude | K79: E1 | R79: Off topic: sensing or security application without protection of sensor/health data
A80: S0073 | B80: OpenAlex | C80: R3 | D80: Intelligent Process Automation for Detecting Unauthorized Entry by Actors in IoT Imbedded Enterprise Setting | E80: Amit K. Nerurkar, G. T. Thampi | F80: 2022 | H80: https://doi.org/10.1007/978-981-19-4193-1_40 | J80: Exclude | K80: E1 | R80: Off topic: sensing or security application without protection of sensor/health data
A81: S0074 | B81: OpenAlex | C81: R3 | D81: Improvement of No2 Gas Sensing Characteristics of Graphene-Sno2 Hybrid Nanocomposites by Proton Irradiation: Experimental and Dft Studies | E81: Ka Yoon Shin, Ali Mirzaei, Thanayut Kaewmaraya, Jae Hoon Bang, Wansik Oum, Dong Jae Yu, Sukwoo Kang, Tanveer Hussain, Sang Sub Kim, Hyoun Woo Kim | F81: 2022 | H81: https://doi.org/10.2139/ssrn.4169565 | J81: Exclude | K81: E1 | R81: Off topic: sensing or security application without protection of sensor/health data
A82: S0075 | B82: OpenAlex | C82: R3 | D82: Determination of Animal-Based and Plant-Based Meat Products with an Electronic Nose Using a Fuzzy Logic Algorithm | E82: Kyla Marie W. Calalang, Vince Samuel R. De Peña, Jocelyn F. Villaverde | F82: 2026 | H82: https://doi.org/10.3390/engproc2026134049 | J82: Exclude | K82: E1 | R82: Off topic: sensing or security application without protection of sensor/health data
A83: S0076 | B83: OpenAlex | C83: R3 | D83: Classification of Local Fish Meat Types in the Philippines Using Electronic Nose | E83: Julius Gabriel Stephen E. Pableo, Prince Albert H. Mangahas, Meo Vincent C. Caya | F83: 2025 | H83: https://doi.org/10.1109/iccae64891.2025.10980567 | J83: Exclude | K83: E1 | R83: Off topic: sensing or security application without protection of sensor/health data
A84: S0077 | B84: OpenAlex | C84: R3 | D84: IoT-Based Integrated Household Gas Monitoring System | E84: Oluwarantimi Eberechukwu Bukola, Momoh J. E. Salami | F84: 2024 | H84: https://doi.org/10.1109/nigercon62786.2024.10927297 | J84: Exclude | K84: E1 | R84: Off topic: sensing or security application without protection of sensor/health data
A85: S0078 | B85: OpenAlex | C85: R3 | D85: Classification of Animal and Plant-Based Edible Oils with Electronic Nose Using Extreme Gradient-Boosted Decision Tree | E85: Reji T. Capoquian, Rance Jacob L. De Guzman, Meo Vincent C. Caya | F85: 2025 | H85: https://doi.org/10.1109/iccae64891.2025.10980599 | J85: Exclude | K85: E1 | R85: Off topic: sensing or security application without protection of sensor/health data
A86: S0079 | B86: OpenAlex | C86: R3 | D86: Home Automation System using Internet-of-Things & Blynk App | E86: Tanishka Bhala, Alok Aggarwal, Shalini Aggarwal, Kshitij Garg, Abhishek Gupta | F86: 2023 | H86: https://doi.org/10.1109/punecon58714.2023.10450120 | J86: Exclude | K86: E1 | R86: Off topic: sensing or security application without protection of sensor/health data
A87: S0080 | B87: OpenAlex | C87: R3 | D87: Gold nanoparticle-sensitized 2D conductive MOF film-based chemiresistors for enhanced identification of American ginseng | E87: Lin-An Cao, Deng-Yue Ma, Yun‐Fei Huo, Hao-Ma, Xiao-Qin Li, Xue-Qin Gu | F87: 2026 | H87: https://doi.org/10.1016/j.microc.2026.119128 | J87: Exclude | K87: E1 | R87: Off topic: sensing or security application without protection of sensor/health data
A88: S0081 | B88: OpenAlex | C88: R3 | D88: A Low-Power DWS-CNN-Based Downsampling Approach for Odor Identification Using Herbal and Organic Datasets | E88: Akshata K. Aldi, Ravindra L. Raibagkar | F88: 2026 | H88: https://doi.org/10.48084/etasr.18175 | J88: Exclude | K88: E1 | R88: Off topic: sensing or security application without protection of sensor/health data
A89: S0082 | B89: OpenAlex | C89: R3 | D89: Sistema de autenticación accesible para el hogar digital | E89: Gonzalo Antón García | F89: 2014 | J89: Exclude | K89: E7 | R89: AI-suggested, confirm. Not peer-reviewed (thesis, podcast, dataset, repository, webinar)
A90: S0083 | B90: OpenAlex | C90: R3 | D90: DriveAware: Intelligent Driver Monitoring and Secure Access Framework for Accident Prevention and Vehicle Safety | E90: Yazhini S, Ajai P, Arun Kumar S, Dharish R, Diya P | F90: 2025 | H90: https://doi.org/10.1109/icicis65613.2025.11371251 | J90: Exclude | K90: E1 | R90: Off topic: sensing or security application without protection of sensor/health data
A91: S0084 | B91: OpenAlex | C91: R3 | D91: IOT-BASED SMART KITCHEN WITH ENHANCED AND AUTOMATED SAFETY MEASURES | E91: Dr. M. Senthil Kumar, Teppala Manoj, V Sirisha, Katakam Bhavyasree, Chikatla Srikar, Dr S Venkata Achuta Rao | F91: 2026 | H91: https://doi.org/10.64751/ijdim.2026.v5.n2(3).1111 | J91: Exclude | K91: E1 | R91: Off topic: sensing or security application without protection of sensor/health data
A92: S0085 | B92: OpenAlex | C92: R3 | D92: Development of a Smart Women Safety ID with Real-Time Gas Detection and Crime-Aware Emergency Alerts System | E92: Pratyusha Chatterjee, Rajnandini Banerjee, Debajyoti Mitra, Tanima Kole Bhowmik | F92: 2025 | H92: https://doi.org/10.70454/jricst.2025.20402 | J92: Exclude | K92: E1 | R92: Off topic: sensing or security application without protection of sensor/health data
A93: S0086 | B93: OpenAlex | C93: R3 | D93: Cloud Computing based Mobile Adhoc Networked Robot for the Establishment of Wireless Communication in Military Hazardous Emergency Response Scenarios | E93: Palvadi Srinivas Kumar, V Praveen Kumar Bejagam, Ranjana Rajdhan, Srivel Ravi | F93: 2020 | J93: Exclude | K93: E1 | R93: Off topic: sensing or security application without protection of sensor/health data
A94: S0087 | B94: OpenAlex | C94: R3 | D94: A colorimetric sensing system for visualization of aroma-contributing volatile organic compounds in food and beverage products | E94: Tianyi Liu | F94: 2024 | H94: https://doi.org/10.32657/10356/182445 | J94: Exclude | K94: E1 | R94: Off topic: sensing or security application without protection of sensor/health data
A95: S0088 | B95: OpenAlex | C95: R3 | D95: (Invited) ppb-Level NO2 Monitoring Using Lung-Inspired MOF on Graphene Hybrids Sensor | E95: Hyeongtae LIM, Hyeok‐jin Kwon, Hongki Kang, Jae Eun Jang, Hyuk‐Jun Kwon | F95: 2024 | H95: https://doi.org/10.1149/ma2024-02372563mtgabs | J95: Exclude | K95: E1 | R95: Off topic: sensing or security application without protection of sensor/health data
A96: S0089 | B96: OpenAlex | C96: R4 | D96: Development of an Electronic Nose Device for Security Applications | E96: Ricardo Macías-Quijas, Autumn Geil, Ramiro Velázquez, A. Lay-Ekuakille | F96: 2019 | H96: https://doi.org/10.1109/concapanxxxix47272.2019.8976974 | J96: Exclude | K96: E1 | R96: Off topic: sensing or security application without protection of sensor/health data
A97: S0090 | B97: OpenAlex | C97: R4 | D97: Odor Sensing System for Safety, Security, and Well‐Being | E97: Takeshi Onodera, Yuanchang Liu | F97: 2026 | H97: https://doi.org/10.1002/tee.70326 | J97: Exclude | K97: E1 | R97: Off topic: sensing or security application without protection of sensor/health data
A98: S0091 | B98: OpenAlex | C98: R4 | D98: Sensor drone for aerial odor mapping for agriculture and security services | E98: Theerapat Pobkrut, Tanthip Eamsa-ard, Teerakiat Kerdcharoen | F98: 2016 | H98: https://doi.org/10.1109/ecticon.2016.7561340 | J98: Exclude | K98: E1 | R98: Off topic: sensing or security application without protection of sensor/health data
A99: S0092 | B99: OpenAlex | C99: R4 | D99: Electronic Nose and Its Applications: A Survey | E99: Diclehan Ulucan, Oguzhan Ulucan, Mehmet Türkan | F99: 2019 | H99: https://doi.org/10.1007/s11633-019-1212-9 | J99: Exclude | K99: E1 | R99: Off topic: sensing or security application without protection of sensor/health data
A100: S0093 | B100: OpenAlex | C100: R4 | D100: Human Odor Security Using E-nose | E100: V. Anush Kumar, V. Anush Kumar, C. S. Manigandaa, S. Dhanush Hariharan, Challapalli Manikantaa, G. Saranya, V. D. Ambeth Kumar, V. D. Ambeth Kumar | F100: 2023 | H100: https://doi.org/10.1007/978-981-99-1051-9_4 | J100: Exclude | K100: E1 | R100: Off topic: sensing or security application without protection of sensor/health data
...

Sheet Included studies
A1: Record ID | B1: Ref. no. in paper | C1: Authors | D1: Year | E1: Title | F1: Venue | G1: DOI / ID | H1: Mechanism | I1: Pipeline stage | J1: Asset protected | K1: Chemical-sensor data (Y/N) | L1: D | M1: F | N1: A | O1: C | P1: M | Q1: N | R1: H(R) | S1: Elements (count) | T1: Charting source | U1: Evidence type for coded elements | V1: Notes | W1: Evidence level | X1: Mechanism category
A2: R0001 | B2: 19 | C2: H. Janjua, W. Joosen, S. Michiels, D. Hughes | D2: 2018 | E2: Trusted Operations on Sensor Data | F2: Sensors 18(5), 1364 | G2: 10.3390/s18051364 | H2: TrustZone (OP-TEE) secure operations on sensor data | I2: Acquisition | J2: Secrecy, integrity, freshness of readings | K2: N | R2: 1 | S2: =SUM(L2:R2) -> 1 | T2: Full text | U2: Implemented and evaluated | V2: Full text read. Raspberry Pi 3 + BLE pulse sensor; timing overhead only; no calibration or drift. | Pulse sensor and camera on Raspberry Pi 3; no gas sensors; evaluation reports timing, not drift or calibration. | W2: Primary synthesis | X2: TEE or enclave
A3: R0003 | B3: 23 | C3: P. Wang, L. Li, Y. Zheng, G. Li | D3: 2021 | E3: High Steady-state Physical Unclonable Function Generator Based on Gas Sensors | F3: J. Electronics & Information Technology 43(6), 1596–1602 | G3: 10.11999/JEIT201104 | H3: Gas-sensor PUF (Pd-SnO2 nanofibers; 8-sensor array, 3-sensor cluster comparisons, 128-bit response) | I3: Device identity | J3: Node identity | K3: Y | L3: 1 | S3: =SUM(L3:R3) -> 1 | T3: Full text | U3: Implemented (Chinese full text read) | V3: Full text read (Chinese full text; English title and abstract; JEIT 43(6):1596-1602, 2021). Formaldehyde stimulus; reliability 97.85% tested only across heater voltage 4.2-4.9 V (5 samples) and a 400 s run at room conditions (100% for 90 s, >95% after); humidity and long-term drift not tested. Uniqueness 49.04%; randomness 97.03% in abstract vs 98.06% in text. No authentication protocol, reading or calibration binding. Elements: D. | Pd-SnO2 sensors, formaldehyde; check whether full text is English (E3 if not). | W3: Primary synthesis | X3: PUF only
A4: R0005 | B4: 17 | C4: Y. Park, Y. Son, H. Shin, D. Kim, Y. Kim | D4: 2016 | E4: This Ain't Your Dose: Sensor Spoofing Attack on Medical Infusion Pump | F4: USENIX WOOT 2016 | G4: woot16-paper-park | H4: Sensor spoofing attack on infusion-pump drop sensor | I4: Transduction | J4: Medical sensor integrity | K4: N | S4: =SUM(L4:R4) -> 0 | T4: Full text | U4: Weakness shown (attack) | V4: Full text read. Laser spoofing from ~12 m; over-infusion up to ~3.3x. Physical attack below any TEE. | Physical spoofing of a medical sensor; supports the transduction threat in Table I. | W4: Primary synthesis | X4: Other (isolation monitor, spoofing attack)
A5: S0020 | B5: 45 | C5: Yang Bin, Wonjun Lee | D5: 2018 | E5: Human Body Odor Based Authentication Using Machine Learning | G5: https://doi.org/10.1109/ssci.2018.8628697 | H5: Gas-sensor odor biometric + ML (K-means, PCA, NN) | I5: Inference | J5: Person identity (I2) | K5: Y | S5: =SUM(L5:R5) -> 0 | T5: Full text | V5: Full text read (IEEE SSCI 2018). Body-odor samples from MQ-series gas sensors; K-means, PCA and neural network identify individuals with high accuracy. Shows odor data are identifying (I2). No protection mechanism. No elements coded. | AI-suggested, confirm. Odor biometric | W5: Primary synthesis | X5: Breath or odor ML
A6: S0022 | B6: 41 | C6: S Rajashree, Rajkumar Sukumar | D6: 2021 | E6: CBC (Cipher Block Chaining)-Based Authenticated Encryption for Securing Sensor Data in Smart Home | G6: https://doi.org/10.1007/978-3-030-71485-7_12 | H6: AES-128-CBC encryption with CBC-MAC for sensor data before transmission | I6: Transmission | J6: Confidentiality and integrity of sensor data in transit | K6: N | S6: =SUM(L6:R6) -> 0 | T6: Full text | V6: Full text read (Springer/EAI chapter, 2021). ESP32 with DHT11 temperature-humidity sensor; timestamped readings written to a file and encrypted with AES-CBC, last block used as MAC. Gas sensors mentioned only as a possible addition, so no chemical-sensor data were used (reclassified from Y). No performance evaluation, device-side protection, freshness, attestation, calibration or model binding. No elements coded. | AI-suggested, confirm. Authenticated encryption of smart-home sensor data | W6: Primary synthesis | X6: Cryptography only
A7: S0026 | B7: 22 | C7: Shuang Hu, Pengjun Wang, Haonan He, Yuejun Zhang, Xiangyu Li | D7: 2024 | E7: Gas Sensor Physically Unclonable Function-Based Lightweight Bidirectional Authentication Protocol for Gas Sensor Networks | G7: https://doi.org/10.3390/electronics13173385 | H7: Gas-sensor PUF (ZnO-SnO2 array) + lightweight bidirectional user-server-node authentication protocol (hash, XOR, nonces), ProVerif-verified | I7: Device identity / transmission | J7: Node authentication; session key for transmitting gas data | K7: Y | L7: 1 | Q7: 1 | S7: =SUM(L7:R7) -> 2 | T7: Full text | U7: D implemented; N formal verification only (ProVerif) | V7: Full text read (Electronics 2024, 13(17), 3385). D: GS-PUF response hashed for node authentication; ethanol and methanol stimuli. N: user and server random numbers per session; formally resists replay, impersonation, node tampering and cloning (ProVerif only, no hardware protocol timing). Gas data sent under a session key (confidentiality), but individual readings are not digested or signed. No calibration, firmware or model binding. Elements: D, N. | AI-suggested, confirm. Gas-sensor PUF authentication protocol | W7: Primary synthesis | X7: PUF only
A8: S0029 | B8: 25 | C8: Xiaowei Zhang, Zexin Ji, Xiangyu Li, Pengjun Wang, Yangong Zheng, Shanshan Wang | D8: 2025 | E8: Design of Gas Sensors-Based PUF for Internet of Things Security | G8: https://doi.org/10.1109/jsen.2025.3540015 | H8: Gas-sensor PUF (TiO2-ZnO nanofibers; 128-bit) | I8: Device identity | J8: Node identity and key management | K8: Y | L8: 1 | S8: =SUM(L8:R8) -> 1 | T8: Full text | U8: Implemented and evaluated | V8: Full text read (IEEE Sensors J. 25(7), 2025). Eight TiO2-ZnO sensors, three per cluster, median averaging filter + multi-bit balancing, 128-bit response; varied gas concentrations and operating voltages; uniqueness 49.6%, randomness 98.6%, reliability 97%. Authentication and key management claimed as applications only, no protocol. Humidity not tested. Elements: D. | AI-suggested, confirm. Gas-sensor PUF (IEEE Sensors J. 2025) | W8: Primary synthesis | X8: PUF only
A9: S0042 | C9: Jaswanth Kumar N, N H Shrinandh, Jayasree M. Oli, Paramasivam C. | D9: 2026 | E9: A Secured Distributed IoT Framework for Real-Time Wildfire Detection using Edge Computing and Spatial-Temporal Correlation | G9: https://doi.org/10.1109/icoei68323.2026.11541877 | H9: ECDSA P-256 message authentication + multi-node consensus (ESP32, MQ gas sensors) | I9: Transmission | J9: Authenticity/integrity of gas readings | K9: Y | S9: =SUM(L9:R9) -> 0 | T9: Abstract only | V9: Charted from abstract only (abstract supplied by author). Wildfire detection; signing at a Python gateway; consensus of 2+ nodes within 500 m. No TEE. | AI-suggested, confirm. Secured sensor framework | W9: Supplementary (abstract only) | X9: Cryptography only
A10: S0046 | C10: V. T. Vithya, M. P. Chandrasekar, M. Suganthy, J. Jasmine Hephzipah, B. Sarala, Nuthakki Praveena, M. Perarasi | D10: 2022 | E10: Crptography based Lifi for Patient Privacy and Emergency Health Service Using IOT | G10: https://doi.org/10.17762/ijritcc.v10i2s.5928 | H10: SHA hashing for LiFi health IoT data | I10: Transmission | J10: Patient vital-sign data | K10: Y | S10: =SUM(L10:R10) -> 0 | T10: Abstract only | V10: Charted from abstract only. Vital-sign kit includes a gas sensor (not breath). Low technical depth. | AI-suggested, confirm. Crypto for health IoT; low technical depth? | W10: Supplementary (abstract only) | X10: Cryptography only
A11: S0051 | B11: 27 | C11: Haitao Mei, Yuejun Zhang, Haonan He, Yangong Zheng | D11: 2023 | E11: Design of High-Performance Gas-Sensing PUF Based on Nanoparticles/Fibers With Composite Morphology | G11: https://doi.org/10.1109/jsen.2023.3312323 | H11: Gas-sensor PUF (EHD nano-SnO2 particle/fiber) + PUF-based gas discrimination scheme | I11: Device identity | J11: Sensor identity; gas discrimination from per-gas PUF difference | K11: Y | L11: 1 | S11: =SUM(L11:R11) -> 1 | T11: Full text | U11: Implemented and evaluated | V11: Full text read (IEEE Sensors J. 23(20), 2023). EHD nano-SnO2 particle/fiber sensors; ethanol and formaldehyde at different temperatures; reliability 99.21%, uniqueness 49.37%, NIST pass. Gas authentication scheme distinguishes two reducing gases by PUF-response difference (min HD 57.1% between gases vs max 3.9% across 4.5-4.7 V): a selectivity aid, not authentication of samples or readings. Humidity not tested. Elements: D. | AI-suggested, confirm. Gas-sensing PUF (IEEE Sensors J. 2023) | W11: Primary synthesis | X11: PUF only
A12: S0056 | B12: 30 | C12: Xiali Han, Shanshan Wang, Jianding Yu, Pengjun Wang, Xiangyu Li | D12: 2026 | E12: Design of PUF based on a Cr2O3-SnO2 gas sensor for Internet of Things security | G12: https://doi.org/10.1016/j.measurement.2026.121395 | H12: Gas-sensor PUF (Cr2O3-SnO2; block-mapped random projection; 128-bit) | I12: Device identity | J12: Node identity and key management | K12: Y | L12: 1 | S12: =SUM(L12:R12) -> 1 | T12: Abstract only | U12: Implemented (per abstract, not verified) | V12: Charted from abstract only (full text unavailable). Uniqueness 50.02%, randomness 98.83%, reliability 97.21%; ML modeling attacks near 0.5 accuracy for 8 models; resistant to environmental disturbance (per abstract). No data binding, TEE, or health use stated. | AI-suggested, confirm. Gas-sensor PUF (Measurement 2026) | W12: Supplementary (abstract only) | X12: PUF only
A13: S0069 | B13: 42 | C13: Sanjay Patidar, Rajni Jindal, Neetesh Kumar | D13: 2024 | E13: A secure and energy-efficient edge computing improved SZ 2.1 hybrid algorithm for handling iot data stream | G13: https://doi.org/10.1007/s11042-024-18765-0 | H13: Error-bounded SZ 2.1 lossy compression + ChaCha20-Poly1305 authenticated encryption at the edge | I13: Transmission | J13: Confidentiality, integrity and authentication of IoT data streams in transit | K13: N | S13: =SUM(L13:R13) -> 0 | T13: Full text | V13: Full text read (Multimed. Tools Appl., 2024). Raspberry Pi client; datasets: driver stress (ECG, HR, GSR, RR) and UCI gas sensors for home activity monitoring, but only the temperature readings of the gas dataset were used, so no chemical-sensor data (reclassified from Y). Per-message Poly1305 MAC with 128-bit nonce; reports energy and processing-time reductions. No device-side protection, attestation, calibration or model binding. No elements coded. | AI-suggested, confirm. Secure IoT data stream | W13: Primary synthesis | X13: Cryptography only
A14: S0206 | B14: 44 | C14: Anna Paleczek, Justyna Grochala, Dominik Grochala, Agnieszka Pręgowska, Magdalena E Osial, Richard O. Oyeleke, Małgorzata Pihut, Jolanta E. Loster, Artur Maciej Rydosz | D14: 2025 | E14: The exhaled breath pattern as a potential method for biometrics identification | G14: https://doi.org/10.1038/s41598-025-19463-z | H14: Portable e-nose + ML (11 MOX/electrochemical sensors) | I14: Inference | J14: Breath profile (attribute inference) (I2) | K14: Y | S14: =SUM(L14:R14) -> 0 | T14: Full text | V14: Full text read. 94 participants; gender predicted from breath at 87.5% accuracy, BMI MAE ~4 kg/m2. Shows breath data reveal personal attributes. Notes sensor drift and need for encryption. | AI-suggested, confirm. Breath as biometric -> re-identification risk | W14: Primary synthesis | X14: Breath or odor ML
A15: S0250 | C15: Ashutosh Desai | D15: 2024 | E15: Person Identification using E-Nose : A quantitative study on identifying individuals based on exhale patterns | H15: IMS e-nose breath identification + 6 ML classifiers | I15: Inference | J15: Person identity from breath (I2) | K15: Y | S15: =SUM(L15:R15) -> 0 | T15: Abstract only | V15: Charted from abstract only. 30 participants, 3 sessions on different days. Ion mobility spectrometry, not chemiresistive. | AI-suggested, confirm. Exhaled-breath identification -> re-identification risk | W15: Supplementary (abstract only) | X15: Breath or odor ML
A16: S0280 | C16: Yusnani Mohd Yussoff, Nazhatul Hafizah Kamarudin, Habibah Hashim | D16: 2017 | E16: Lightweight Trusted Authentication Protocol for Wireless Sensor Network (WSN) | H16: Trusted (TCG-based) authentication protocol for WSN | I16: Device identity | J16: Node authenticity against clone/false messages | K16: N | S16: =SUM(L16:R16) -> 0 | T16: Abstract only | V16: Charted from abstract only. Suggests e-health use. | AI-suggested, confirm. Trusted auth for WSN, e-health use | W16: Supplementary (abstract only) | X16: Cryptography only
A17: S0287 | B17: 48 | C17: Edlira Dushku, Jeppe Hagelskjar Ostergaard, Nicola Dragoni | D17: 2022 | E17: Memory Offloading for Remote Attestation of Multi-Service IoT Devices | G17: https://doi.org/10.3390/s22124340 | H17: TrustZone-M attestation with memory offloading incl. peripheral registers (ERAMO) | I17: Acquisition | J17: Sensor-peripheral configuration integrity | K17: N | N17: 1 | S17: =SUM(L17:R17) -> 1 | T17: Full text | U17: Implemented and evaluated | V17: Full text read (Sensors 22(12), 4340, 2022; rechecked 2026-10-17). LPC55S69 (TrustZone-M), FreeRTOS. Attests all readable memory incl. memory-mapped peripheral registers; verifier checks I2C peripheral CFG/INTENSET/CLKDIV and BME280 configuration bits in ctrl_hum (0xF2), ctrl_meas (0xF4) and config (0xF5), i.e. acquisition settings (MITC field A). ADC configuration discussed as a risk but not verified; analog water-level sensor not attested; readings (dynamic registers) excluded. ~3.94 s combined attestation at 806,400 baud. | AI-suggested, confirm. ERAMO: attests peripheral memory on TrustZone MCU | W17: Primary synthesis | X17: TEE or enclave
A18: S0292 | B18: 31 | C18: Kota Yoshida, Kuniyasu Suzaki, Takeshi Fujino | D18: 2021 | E18: Towards Trusted IoT Sensing Systems: Implementing PUF as Secure Key Generator for Root of Trust and Message Authentication Code | G18: https://doi.org/10.1145/3505253.3505258 | H18: PUF-attested TEE (RISC-V Keystone) on main device + PUF-based MAC on subordinate sensor | I18: Acquisition / processing | J18: Reading authenticity from correct device + attested processing | K18: N | L18: 1 | M18: 1 | R18: 1 | S18: =SUM(L18:R18) -> 3 | T18: Full text | U18: Implemented and evaluated | V18: Full text read (HASP 2021 workshop, ACM). Main device: PRINCE glitch PUF as root of trust for RISC-V Keystone on FPGA; remote attestation of device key, security-monitor hash and enclave hash. Sensor: CMOS image-sensor PUF simulated on Raspberry Pi over Ethernet; per-image MAC (CMAC/HMAC) verified in enclave, ~18-19 ms per 640x480 image. Elements: D, F, H(R). Confidentiality out of scope; no freshness/replay protection for readings stated; no calibration or model binding. | AI-suggested, confirm. PUF root of trust + MAC for IoT sensing | W18: Primary synthesis | X18: TEE or enclave
A19: S0294 | B19: 36 | C19: Hamid Reza Ghaeini, Matthew Chan, Raad Bahmani, Ferdinand Brasser, Garcia, Luis, Jianying Zhou, Ahmad‐Reza Sadeghi, Nils Ole Tippenhauer, Saman Zonouz | D19: 2019 | E19: PAtt: Physics-based Attestation of Control Systems | G19: https://doi.org/10.60882/cispa.24612948 | H19: Physics-based software attestation without trusted hardware: nonce-seeded hash of PLC logic encoded as actuation, verified from resulting sensor traces | I19: Acquisition / control | J19: Integrity of PLC logic and authenticity of attestation sensor readings | K19: N | L19: 1 | M19: 1 | Q19: 1 | S19: =SUM(L19:R19) -> 3 | T19: Full text | U19: Implemented and evaluated | V19: Full text read (RAID 2019). Siemens S7-1200 PLC + robot arm testbed. F: hash over PLC logic code blocks. N: fresh verifier nonce in each attestation. D: verifier identifies each PLC and physical system by its process noise signature (PUF-like). Detects manipulated logic and replayed/spoofed sensor readings with 97% accuracy. Sensor readings serve as attestation evidence only; routine readings are not digested or signed (H(R) not coded). No calibration, model or acquisition-config binding. Elements: D, F, N. | AI-suggested, confirm. Binds attestation to physical sensor traces | W19: Primary synthesis | X19: Attestation without TEE
A20: S0297 | C20: Ivan De Oliveira Nunes, Xuhua Ding, Gene Tsudik | D20: 2021 | E20: On the Root of Trust Identification Problem | G20: https://doi.org/10.1145/3412382.3458274 | H20: Root-of-trust identification problem | I20: Device identity | J20: Which physical device produced a sensed value | K20: N | S20: =SUM(L20:R20) -> 0 | T20: Abstract only | V20: Charted from abstract only. Problem analysis for TEE-based sensing and actuation. | AI-suggested, confirm. Which device holds the RoT; sensing | W20: Supplementary (abstract only) | X20: Attestation without TEE
A21: S0298 | C21: Hong Zhong, Wenwen Cao, Qingyang Zhang, Jing Zhang, Jie Cui | D21: 2021 | E21: Toward Trusted and Secure Communication Among Multiple Internal Modules in CAV | G21: https://doi.org/10.1109/jiot.2021.3082542 | H21: Remote attestation + HMAC for in-vehicle module data (Intel SGX) | I21: Transmission | J21: Integrity of sensed data between modules | K21: N | S21: =SUM(L21:R21) -> 0 | T21: Abstract only | V21: Charted from abstract only (abstract supplied by author). Proven secure under CDH in the random oracle model. | AI-suggested, confirm. | W21: Supplementary (abstract only) | X21: TEE or enclave
A22: S0300 | C22: Mohamed A. El-Zawawy, Harsha Vasudev, Mauro Conti | D22: 2024 | E22: BDMFA: Forensic-enabling attestation technique for Internet of Medical Things | G22: https://doi.org/10.1016/j.iot.2024.101464 | H22: Blockchain + deep-learning medical attestation (SMART-based) | I22: Acquisition / analytics | J22: Medical sensor reading consistency; attestation history | K22: N | S22: =SUM(L22:R22) -> 0 | T22: Abstract only | V22: Charted from abstract only. Uses inconsistent medical sensor readings as compromise signal; 50 patient-sensors, 2.6 s attestation (simulation). | AI-suggested, confirm. IoMT attestation using medical sensor readings; SMART-based | W22: Supplementary (abstract only) | X22: Attestation without TEE
A23: S0313 | C23: I.O. Shevtsov, Tetiana Fesenko | D23: 2026 | E23: Developing a task allocation model for remote health monitoring in smart cities, considering latency, energy consumption, and privacy on fog nodes | G23: https://doi.org/10.15587/2706-5448.2026.358187 | H23: TEE + RATS attestation for fog offloading of patient monitoring | I23: Analytics | J23: Patient data confidentiality on fog nodes | K23: N | S23: =SUM(L23:R23) -> 0 | T23: Abstract only | V23: Charted from abstract only. Simulation (YAFS); ECG/audio tasks. | AI-suggested, confirm. TEE + RATS attestation on fog nodes for remote patient monitoring (simulation) | W23: Supplementary (abstract only) | X23: TEE or enclave
A24: S0317 | B24: 33 | C24: Yongzhi Wang | D24: 2026 | E24: TEE Protected Drone Inspection for Critical Infrastructure: Securing Edge Analytics and Trust at Scale | G24: https://doi.org/10.54941/ahfe1007075 | H24: Attested enclave (platform unnamed) with attestation-gated mission key, in-enclave autoencoder anomaly detection, enclave-signed results | I24: Processing / transmission | J24: Confidentiality and integrity of sensor-derived results | K24: N | M24: 1 | S24: =SUM(L24:R24) -> 1 | T24: Full text | U24: Design only (no evaluation) | V24: Full text read (AHFE/IHSI 2026, open access; read via web reader). UAV infrastructure inspection. Pre-flight remote attestation of enclave measurement (F); mission key provisioned after attestation; results encrypted and signed with enclave key bound to attested instance (result signing, not per-reading digest). Autoencoder in enclave flags anomalous frames (no architecture, threshold or accuracy given). No freshness/nonce, model version, calibration or device identity. Design with qualitative security analysis only; no implementation or quantitative evaluation. Elements: F. | AI-suggested, confirm. TEE edge analytics of sensor data | W24: Primary synthesis | X24: TEE or enclave
A25: S0318 | C25: Francesco Alesiani, Sebastian Gajek | D25: 2016 | E25: Remote Testimony: How to Trust an Autonomous Vehicle | G25: https://doi.org/10.1109/vtcspring.2016.7504447 | H25: Remote testimony from signing, tamper-resistant sensors (no trusted computing) | I25: Acquisition | J25: Reliability of vehicle sensor data to peers | K25: N | S25: =SUM(L25:R25) -> 0 | T25: Abstract only | V25: Charted from abstract only (abstract supplied by author). | AI-suggested, confirm. | W25: Supplementary (abstract only) | X25: Attestation without TEE
A26: S0320 | C26: Ivan De Oliveira Nunes, Karim Eldefrawy, Norrathep Rattanavipanon, Gene Tsudik | D26: 2019 | E26: A Verified Architecture for Proofs of Execution on Remote Devices under Full Software Compromise | G26: https://doi.org/10.48550/arxiv.1908.02444 | H26: Formally verified proofs of execution binding outputs to code (VAPE/APEX) | I26: Acquisition | J26: Authenticity of sensor data produced by expected code | K26: N | S26: =SUM(L26:R26) -> 0 | T26: Full text | V26: Full text read. arXiv version; MSP430/AVR; low overhead. Check published version (APEX, USENIX Security 2020) for citation. | AI-suggested, confirm. VAPE: authenticated sensing on low-end MCUs | W26: Primary synthesis | X26: Attestation without TEE
A27: S0324 | B27: 40 | C27: Sergio Benlloch-Lopez, Miquel Viel-Vazquez, Javier Naranjo-Alcazar, Jordi Grau-Haro, Pedro Zuccarello | D27: 2026 | E27: Threat Modeling for Enhancing Security of IoT Audio Classification Devices Under a Secure Protocols Framework | G27: https://doi.org/10.1007/978-3-032-24807-7_45 | H27: TPM 2.0 measured boot and remote attestation gating a one-time LUKS unlock key; mTLS 1.3 with post-quantum hybrid; signed, versioned ML model updates; tamper sensors (no TEE) | I27: Acquisition / inference / transmission | J27: Audio features, on-device models, data at rest | K27: N | M27: 1 | P27: 1 | S27: =SUM(L27:R27) -> 2 | T27: Full text | U27: Design only (evaluation planned) | V27: Full text read (arXiv:2509.14657v3, Nov 2025; published Springer 2026). Raspberry Pi 4 + TPM 2.0 prototype design. F: boot stages measured into TPM PCRs, quote verified by server. M: model updates signed and version-controlled; rollback here means redeploying an earlier trusted version, not anti-rollback protection. Feature hashes and E2E encryption protect data in transit (not coded as per-reading digest). No freshness, calibration or acquisition-config binding. Evaluation planned only, no results. Elements: F, M. | AI-suggested, confirm. Sensor ML device threat model | W27: Primary synthesis | X27: Attestation without TEE
A28: S0327 | B28: 35 | C28: Antonio J. Cabrera-Gutiérrez, Encarnación Castillo, Antonio Escobar-Molero, Juan Cruz-Cozar, Diego Pedro Morales, Luis Parrilla | D28: 2023 | E28: Secure Sensor Prototype Using Hardware Security Modules and Trusted Execution Environments in a Blockchain Application: Wine Logistic Use Case | G28: https://doi.org/10.3390/electronics12132987 | H28: TF-M TEE + HSM signing sensor readings with timestamp | I28: Acquisition | J28: Reading authenticity and freshness | K28: N | Q28: 1 | R28: 1 | S28: =SUM(L28:R28) -> 2 | T28: Full text | U28: Implemented and evaluated | V28: Full text read. PSoC64, DPS310 pressure sensor; 1.09x vs hardware-HSM baseline. No calibration handling. | AI-suggested, confirm. HSM + TEE secure sensor | W28: Primary synthesis | X28: TEE or enclave
A29: S0329 | C29: Yin Liu, Breno Dantas Cruz, Eli Tilevich | D29: 2023 | E29: Trusted and privacy-preserving sensor data onloading | G29: https://doi.org/10.1016/j.comcom.2023.04.027 | H29: TEE middleware (Open-TEE on Android) + adaptive differential privacy + Trust-Data theory for spurious-data removal in sensor-data onloading | I29: Analytics | J29: Sensor-data privacy; detection of spurious data | K29: N | S29: =SUM(L29:R29) -> 0 | T29: Full text | V29: Full text read (author manuscript, Computer Communications 2023). Extended version of S0328. Apps deposit sensor data (e.g., geolocation, blood pressure) in a TEE-protected middleware that answers noisy statistical queries. No signing, attestation, freshness, calibration or model binding. No elements coded. | AI-suggested, confirm. | W29: Primary synthesis | X29: TEE or enclave
A30: S0330 | C30: Saeed Mirzamohammadi, Ardalan Amiri Sani | D30: 2018 | E30: Viola: Trustworthy Sensor Notifications for Enhanced Privacy on Mobile Systems | G30: https://doi.org/10.1109/tmc.2018.2812706 | H30: Verified sensor/indicator invariants enforced in kernel/hypervisor (Viola) | I30: Acquisition | J30: Sensor-access privacy | K30: N | S30: =SUM(L30:R30) -> 0 | T30: Full text | V30: Full text read. Read via author dissertation chapter. Camera/mic; Nexus 5, ODROID. | AI-suggested, confirm. | W30: Primary synthesis | X30: Other (isolation monitor, spoofing attack)
A31: S0331 | C31: Hongcheng Xie, Yu Guo, Xiaohua Jia | D31: 2021 | E31: Privacy-Preserving Location-Based Data Queries in Fog-Enhanced Sensor Networks | G31: https://doi.org/10.1109/jiot.2021.3135303 | H31: Somewhat homomorphic encryption + Intel SGX for location-based sensor queries | I31: Analytics | J31: Confidentiality of queries, sensor locations, sensor data | K31: N | S31: =SUM(L31:R31) -> 0 | T31: Abstract only | V31: Charted from abstract only (abstract supplied by author). | AI-suggested, confirm. | W31: Supplementary (abstract only) | X31: TEE or enclave
A32: S0332 | C32: Xin Liu, Zhenbin Guo, Jun Ma, Yuchen Song | D32: 2021 | E32: A Secure Authentication Scheme for Wireless Sensor Networks Based on DAC and Intel SGX | G32: https://doi.org/10.1109/jiot.2021.3097996 | H32: Dynamic authentication credentials + SGX-protected master key in WSN gateway | I32: Device identity | J32: Access to WSN data; authentication-table protection | K32: N | S32: =SUM(L32:R32) -> 0 | T32: Abstract only | V32: Charted from abstract only (abstract supplied by author). BAN logic, AVISPA, NS3 simulation. | AI-suggested, confirm. SGX for WSN auth | W32: Supplementary (abstract only) | X32: TEE or enclave
A33: S0333 | C33: Anil Yadav, Nitin Rakesh, Sujata Pandey, Rajat Kumar Singh | D33: 2019 | E33: Optimising the DTLS handshake design for TEE enabled sensor nodes | G33: https://doi.org/10.1504/ijsn.2019.101416 | H33: TEE-based DTLS handshake for sensor nodes | I33: Transmission | J33: Session keys for sensor data | K33: N | S33: =SUM(L33:R33) -> 0 | T33: Abstract only | V33: Charted from abstract only (abstract supplied by author). Lower memory footprint, small handshake-time penalty. | AI-suggested, confirm. TEE sensor nodes | W33: Supplementary (abstract only) | X33: TEE or enclave
A34: S0337 | B34: 38 | C34: Jonathan Heiss, Anselm Busse, Stefan Tai | D34: 2021 | E34: Trustworthy Pre-processing of Sensor Data in Data On-Chaining Workflows for Blockchain-Based IoT Applications | G34: https://doi.org/10.1007/978-3-030-91431-8_9 | H34: Trustworthy pre-processing of signed sensor data off-chain with Intel SGX (remote attestation) or zkSNARKs (ZoKrates) before blockchain | I34: Processing | J34: End-to-end integrity of pre-processed sensor data | K34: N | L34: 1 | M34: 1 | R34: 1 | S34: =SUM(L34:R34) -> 3 | T34: Full text | U34: Implemented and evaluated | V34: Full text read (arXiv:2110.15869, author version of ICSOC 2021, LNCS 13121). Sensor nodes sign measurements with a sensor key pair; gateway verifies signatures inside the enclave or proof and proves correct transformation (filtering, aggregation). SGX enclave verified by remote attestation. Proof-of-concept on smart-meter data; enclave pre-processing orders of magnitude faster than zkSNARKs; on-chain verification cost in gas. Pre-processing is generic data reduction; calibration not mentioned. Elements: D, F, H(R). | AI-suggested, confirm. TEE pre-processing of sensor data (relevant to calibration stage) | W34: Primary synthesis | X34: TEE or enclave
A35: S0340 | C35: Anil Yadav, Sujata Pandey, Rajat Kumar Singh, Nitin Rakesh | D35: 2020 | E35: Design of Psk Based Trusted Dtls for Smart Sensor Nodes | G35: https://doi.org/10.2174/2666255813999200708135353 | H35: TEE-based PSK DTLS handshake for smart sensor nodes | I35: Transmission | J35: Session keys for sensor data | K35: N | S35: =SUM(L35:R35) -> 0 | T35: Abstract only | V35: Charted from abstract only (abstract supplied by author). Handshake penalty cut from ~3.5 to ~1.5 ms. Extends S0333 (different handshake mode). | AI-suggested, confirm. TEE sensor nodes | W35: Supplementary (abstract only) | X35: TEE or enclave
A36: S0344 | B36: 32 | C36: Tatsuya Oyama, Manami Hagizaki, Shunsuke Okura, Takeshi Fujino | D36: 2024 | E36: Implementation of an Image Tampering Detection System with a CMOS Image Sensor PUF and OP-TEE | G36: https://doi.org/10.3390/s24227121 | H36: CMOS image-sensor PUF key + HMAC per frame, verified in OP-TEE | I36: Acquisition / inference | J36: Reading authenticity before ML inference | K36: N | L36: 1 | R36: 1 | S36: =SUM(L36:R36) -> 2 | T36: Full text | U36: Implemented and evaluated | V36: Full text read. ZCU104; worst-case 4-bit error in 132,000 regenerations; MAC overhead ~0.017%/frame. Closest precedent to MITC sensor-reading binding; tested in one environment only. | AI-suggested, confirm. Sensor PUF + OP-TEE: closest analog to MITC sensor binding | W36: Primary synthesis | X36: TEE or enclave
A37: S0345 | C37: Gregor Haas, Micheal Chung, David Kohlbrenner | D37: 2025 | E37: Enabling Confidential I/O on RISC-V Without Hardware Modifications | G37: https://doi.org/10.1145/3733801.3764196 | H37: Confidential I/O on RISC-V via PMP: driver enclaves on a modified Keystone compartmentalize peripheral drivers (sensors, accelerators) | I37: Acquisition / processing | J37: Confidentiality and integrity of peripheral data against untrusted drivers and OS | K37: N | S37: =SUM(L37:R37) -> 0 | T37: Full text | V37: Full text read (ACM CPSIoTSec 2025 workshop). Polarfire Icicle FPGA testbench with an ML accelerator (VTA) and an end-to-end inference application; stock RISC-V, software only. Peripheral isolation; enclaves can produce attestation reports but no per-reading evidence, freshness, calibration or model binding. No calibration mentioned. No elements coded (isolation, not evidence binding). | AI-suggested, confirm. Confidential peripheral I/O | W37: Primary synthesis | X37: TEE or enclave
A38: S0346 | B38: 34 | C38: Shengtuo Hu, Qi Alfred Chen, Jiwon Joung, Can Carlak, Yiheng Feng, Zhuoqing Morley Mao, Henry X. Liu | D38: 2020 | E38: CVShield | G38: https://doi.org/10.1145/3375706.3380552 | H38: TrustZone (OP-TEE) secure peripheral access for GPS reading; planned relocation of processing, encapsulation and transmission code via program slicing (CVShield) | I38: Acquisition | J38: Integrity of GPS readings against a compromised normal world | K38: N | S38: =SUM(L38:R38) -> 0 | T38: Full text | V38: Full text read (ACM AutoSec 2020 workshop, 4 pages). i.MX6 Cortex-A9; CSU/TZASC restrict GPS UART to secure world; ~0.686 ms per 7.91-byte poll. Only sensor reading implemented; processing, packet encapsulation and transmission are future work. No signing, digest, freshness, attestation, calibration or model binding. Hardware attacks such as GPS spoofing out of scope. No elements coded (isolation, not evidence binding). | AI-suggested, confirm. | W38: Primary synthesis | X38: TEE or enclave
A39: S0349 | B39: 47 | C39: Mulong Luo, G. Edward Suh | D39: 2022 | E39: WIP: Interrupt Attack on TEE-protected Robotic Vehicles | G39: https://doi.org/10.14722/autosec.2022.23001 | H39: Attack on TEE-protected sensor timestamping (interrupt injected between sensor read and clock read) | I39: Acquisition | J39: Timestamp (freshness) integrity of sensor data | K39: N | S39: =SUM(L39:R39) -> 0 | T39: Full text | U39: Weakness shown (attack) | V39: Full text read (NDSS AutoSec 2022 workshop, WIP). Intel SGX with SGX-Step interrupts; ROS with a simulated Jackal robot in Gazebo; timestamp error grows with interrupt interval and causes obstacle-localization errors. Shows TEE memory and trusted-clock protection do not ensure timestamp integrity; countermeasures left open. Attack study; no elements coded. | AI-suggested, confirm. Attack on TEE-protected sensing | W39: Primary synthesis | X39: TEE or enclave
A40: S0351 | C40: Renju Liu, Mani B. Srivastava | D40: 2018 | E40: VirtSense | G40: https://doi.org/10.1145/3268935.3268937 | H40: TrustZone virtual sensor instances (VirtSense) | I40: Acquisition | J40: Sensor access control and isolation | K40: N | S40: =SUM(L40:R40) -> 0 | T40: Abstract only | V40: Charted from abstract only. Abstract read on CPS-VO. | AI-suggested, confirm. Trusted sensor virtualization | W40: Supplementary (abstract only) | X40: TEE or enclave
A41: S0352 | B41: 37 | C41: Saad Bin Shams, Emanuel Regnath, Andreas Bogner, Sebastian Steinhorst | D41: 2023 | E41: Trusted Single-Source Sensors using SNARKs | G41: https://doi.org/10.1109/coins57856.2023.10189292 | H41: TEE (Arm TrustZone in design) signs readings; AD-SNARK proofs that statistics (moving average, sliding variance) were computed correctly over authenticated data; PKI device certificate | I41: Acquisition / processing | J41: Authenticity of readings and integrity of processed statistics | K41: N | L41: 1 | R41: 1 | S41: =SUM(L41:R41) -> 2 | T41: Full text | U41: Prototype with simulated sensor; TEE part not evidently implemented | V41: Full text read (IEEE COINS 2023). D: device key generated in secure world, X.509 certificate from manufacturer PKI. H(R): readings signed inside TEE and used as authenticated SNARK inputs. Implementation on a laptop with a simulated temperature sensor; partial Raspberry Pi 3 port (proof generation ~60 ms, verification ~230 ms); TEE part not evidently implemented. No freshness/nonce, firmware attestation, calibration or model binding. Elements: D, H(R). | AI-suggested, confirm. Cryptographic proof of sensor processing | W41: Primary synthesis | X41: TEE or enclave
A42: S0356 | C42: Denghui Zhang, Lijing Ren, Muhammad Faisal Shafiq, Zhaoquan Gu | D42: 2023 | E42: A Privacy Protection Framework for Medical Image Security without Key Dependency Based on Visual Cryptography and Trusted Computing | G42: https://doi.org/10.1155/2023/6758406 | H42: Visual cryptography + privacy-preserving recognition of medical images | I42: Inference | J42: Medical image confidentiality | K42: N | S42: =SUM(L42:R42) -> 0 | T42: Abstract only | V42: Charted from abstract only. | AI-suggested, confirm. | W42: Supplementary (abstract only) | X42: Cryptography only
A43: S0357 | C43: Carlton Shepherd, Raja Naeem Akram, Konstantinos Markantonakis | D43: 2017 | E43: Towards trusted execution of multi-modal continuous authentication schemes | G43: https://doi.org/10.1145/3019612.3019652 | H43: Intel SGX / secure elements for continuous authentication from sensor data | I43: Inference | J43: Integrity/confidentiality of sensor-based authentication decisions | K43: N | S43: =SUM(L43:R43) -> 0 | T43: Abstract only | V43: Charted from abstract only (abstract supplied by author). No significant performance penalty. | AI-suggested, confirm. TEE processing of sensor data for auth | W43: Supplementary (abstract only) | X43: TEE or enclave
A44: S0359 | C44: Igor Zavalyshyn, Nuno Santos, Ramin Sadre, Axel Legay | D44: 2020 | E44: My House, My Rules: A Private-by-Design Smart Home Platform | G44: https://doi.org/10.1145/3448891.3450333 | H44: Intel SGX private-by-design smart-home platform (PatrIoT) | I44: Analytics | J44: Sensor data confidentiality from cloud provider | K44: N | S44: =SUM(L44:R44) -> 0 | T44: Abstract only | V44: Charted from abstract only. | AI-suggested, confirm. Private-by-design sensor platform | W44: Supplementary (abstract only) | X44: TEE or enclave
A45: S0361 | C45: Mengmei Ye, Nianhang Hu, Sheng Wei | D45: 2016 | E45: Lightweight secure sensing using hardware isolation | G45: https://doi.org/10.1109/icsens.2016.7808904 | H45: TrustZone hardware isolation of sensors (Zynq-7000) | I45: Acquisition | J45: Sensor data privacy/integrity | K45: N | S45: =SUM(L45:R45) -> 0 | T45: Abstract only | V45: Charted from abstract only. Abstract read on CPS-VO; low overhead. | AI-suggested, confirm. Hardware-isolated sensing | W45: Supplementary (abstract only) | X45: TEE or enclave
A46: S0362 | C46: Richard Searle, Prabhanjan Gururaj, Shreyas Gaikwad, Kiran Kannur | D46: 2023 | E46: Secure federated machine learning for distributed spectrum sensing in communication networks | G46: https://doi.org/10.1117/12.2663765 | H46: Confidential-computing federated learning with TEE attestation for spectrum sensing | I46: Training | J46: Training data privacy and model integrity | K46: N | S46: =SUM(L46:R46) -> 0 | T46: Abstract only | V46: Charted from abstract only (abstract supplied by author). Simulated sensor network; proposes PUF-encrypted raw data as future work. | AI-suggested, confirm. Confidential FL for sensing | W46: Supplementary (abstract only) | X46: TEE or enclave
A47: S0367 | B47: 39 | C47: Lennart Almstedt, Leander Jehl, Lars Christian Wolf | D47: 2025 | E47: ImageBox: Small-Scale Blockchain-Aided Trusted Machine Learning Inference | G47: https://doi.org/10.1109/percomworkshops65533.2025.00032 | H47: TEE + tamper-proof (single-node blockchain) storage of models, inputs and outputs (ImageBox) | I47: Inference | J47: Integrity of ML inference on sensor data | K47: N | M47: 1 | P47: 1 | R47: 1 | S47: =SUM(L47:R47) -> 3 | T47: Full text | U47: Implemented and evaluated | V47: Full text read (IEEE PerCom Workshops 2025). Classifier in an Intel SGX enclave (LibraryOS/WASM); single-node blockchain (ContractBox) as tamper-evident storage recording model data, input (or its hash), and result; smart contract remotely attests the classifier enclave. Sensors assumed trusted (out of scope). About 35% overhead. Elements: F, M, H(R); M covers model identity bound to the result, not versioning or rollback policy. | AI-suggested, confirm. | W47: Primary synthesis | X47: TEE or enclave
A48: S0372 | B48: 43 | C48: Lanlan Li, Charles Z. Liu, Kejia Huang, Ruiyi Deng, Majed Abdullah Alrowaily, Mansoor Alghamdi, Ibrahim S. Alkhazi, Malek Alrashidi | D48: 2026 | E48: Trust-Aware Environmental State Consensus for Smart Agriculture with TEE-Enabled Sensing and Byzantine-Resilient Blockchain Coordination | G48: https://doi.org/10.3390/s26144577 | H48: TrustZone-M sensing + OP-TEE gateways + Byzantine-resilient aggregation | I48: Acquisition / analytics | J48: Authenticated sensor outputs; consensus | K48: Y | S48: =SUM(L48:R48) -> 0 | T48: Full text | V48: Full text read. Sensors include CO2 (gas, non-chemiresistive). Attack model lists calibration deviations, but no calibration protection is described. TEE does not guarantee reading correctness. | AI-suggested, confirm. TEE-enabled environmental sensing | W48: Primary synthesis | X48: TEE or enclave
A49: S0373 | B49: 46 | C49: Md Shihabul Islam, Mahmoud Zamani, Kevin W. Hamlen, Latifur R. Khan, Murat Kantarcıoğlu | D49: 2024 | E49: Ensuring End-to-End IoT Data Security and Privacy Through Cloud-Enhanced Confidential Computing | G49: https://doi.org/10.1007/978-3-031-65172-4_5 | H49: Memory-access-pattern attack on TEE IoT pipelines + data-oblivious execution and padding (SecIoTT) | I49: Analytics | J49: Sensor-reading confidentiality inside TEEs | K49: N | S49: =SUM(L49:R49) -> 0 | T49: Full text | U49: Weakness shown (attack) | V49: Full text read (DBSec 2024, LNCS 14901, pp. 71-91). Trigger-action IoT automation platform in an Intel SGX enclave in an untrusted cloud, devices assumed to have Arm TrustZone, MQTT transport. Memory access patterns reveal device type (~95%) and values such as temperature (~85%); oblivious execution and padding reduce these to <=27% and <=19%. No elements coded (attack and confidentiality defense). | AI-suggested, confirm. End-to-end confidential computing for IoT data | W49: Primary synthesis | X49: TEE or enclave
A50: S0379 | C50: Sachin S. Shetty, Xueping Liang, Daniel Bowden, Juan Zhao, Lingchen Zhang | D50: 2018 | E50: Blockchain-Based Decentralized Accountability and Self-Sovereignty in Healthcare Systems | G50: https://doi.org/10.1007/978-3-319-99058-3_5 | H50: Permissioned blockchain + Intel SGX for wearable health-data integrity and privacy | I50: Analytics | J50: Personal health data integrity, privacy, accountability | K50: N | S50: =SUM(L50:R50) -> 0 | T50: Abstract only | V50: Charted from abstract only (abstract supplied by author). Extended version of S0347. | AI-suggested, confirm. | W50: Supplementary (abstract only) | X50: TEE or enclave
A51: S0386 | C51: Joseph I. Choi, Dave Jing Tian, Tyler B. Ward, Kevin R. B. Butler, Patrick Traynor, John M. Shea, Tan F. Wong | D51: 2019 | E51: Enclave-based privacy-preserving localization | G51: https://doi.org/10.1145/3317549.3326307 | H51: SGX enclaves for privacy-preserving particle-filter localization | I51: Analytics | J51: Sensor location privacy | K51: N | S51: =SUM(L51:R51) -> 0 | T51: Abstract only | V51: Charted from abstract only (abstract supplied by author). +16 ms vs unprotected; cryptographic alternatives orders of magnitude slower. | AI-suggested, confirm. | W51: Supplementary (abstract only) | X51: TEE or enclave
A52: S0396 | C52: Pav C Suriyanarayanan, Radu Iacob | D52: 2026 | E52: Securing the AI-Driven Vehicle: A Hardware-Based Security Framework for Scalable, Trustworthy Autonomy | G52: https://doi.org/10.4271/2026-01-0085 | H52: Layered hardware security (interface security, SRAM PUF keys, secure boot) for AV sensor-to-compute paths | I52: Acquisition / transmission | J52: Integrity of sensor interfaces (MIPI, Ethernet, PCIe) | K52: N | S52: =SUM(L52:R52) -> 0 | T52: Abstract only | V52: Charted from abstract only (abstract supplied by author). Architecture proposal; no evaluation reported in abstract. | AI-suggested, confirm. | W52: Supplementary (abstract only) | X52: PUF only
A53: S0411 | B53: 24 | C53: Haonan He, Pengjun Wang, Xiangyu Li, Yuejun Zhang, Xiaowei Zhang | D53: 2024 | E53: Highly Reliable RS-PUF Based on Reconfigurable Gas Sensor Array | G53: https://doi.org/10.1109/jsen.2024.3375872 | H53: Gas-sensor PUF (reconfigurable ZnO-SnO2 array) | I53: Device identity | J53: Sensor-node identity for gas sensor networks | K53: Y | L53: 1 | S53: =SUM(L53:R53) -> 1 | T53: Full text | U53: Implemented and evaluated | V53: Full text read (IEEE Sensors J. 24(10), 2024). ZnO-SnO2 sensors with reconfigurable array and reconstruction strategy; ethanol 200-800 ppm; uniqueness 52.4%, randomness 99.1%, reliability 98.17%; BER at 4.5 V and 500 ppm; reliability over 20 days. Humidity not tested. No protocol, reading or calibration binding. Elements: D. | AI-suggested, confirm. Gas-sensor PUF (IEEE Sensors J. 2024) | W53: Primary synthesis | X53: PUF only
A54: S0414 | B54: 26 | C54: Zhanbo Chen, Shanshan Wang, Xiaowei Zhang, Hao Ye, Pengjun Wang, Xiangyu Li | D54: 2026 | E54: A High-Reliability Gas-Sensor-Based PUF for Secure IoT | G54: https://doi.org/10.1109/jsen.2026.3701345 | H54: Gas-sensor PUF (WO2.90; challenge-response, 128-bit) | I54: Device identity | J54: Cryptographic keys from sensor nanostructure | K54: Y | L54: 1 | S54: =SUM(L54:R54) -> 1 | T54: Full text | U54: Implemented and evaluated | V54: Full text read (IEEE Sensors J. 26(14), 2026). Sixteen WO2.90 sensors, multidimensional resistive arbitration, 10,000 CRPs; uniqueness 50.02%, average BER 1.45%; reliability >97% across supply voltage, worst 96.1% over 20-80 C, tracked over 100 days of aging; NIST SP 800-22 pass, min-entropy 127.84/128 bits; LR/SVM/RF/MLP modeling attacks near 50%. Humidity not tested. No protocol, reading or calibration binding. Elements: D. | AI-suggested, confirm. Gas-sensor PUF (IEEE Sensors J. 2026) | W54: Primary synthesis | X54: PUF only
A55: S0419 | B55: 28 | C55: Haonan He, Pengjun Wang, Xiangyu Li, Li Ni, Yuejun Zhang | D55: 2023 | E55: Highly Reliable Physical Unclonable Function Based on ZnO-SnO2 Gas Sensor | G55: https://doi.org/10.1109/asicon58565.2023.10396120 | H55: Gas-sensor PUF (ZnO-SnO2 nanofibers; 128-bit) | I55: Device identity | J55: Sensing-node identity | K55: Y | L55: 1 | S55: =SUM(L55:R55) -> 1 | T55: Full text | U55: Implemented and evaluated | V55: Full text read (IEEE ASICON 2023, 4 pages). Eight ZnO-SnO2 sensors, three per cluster, median averaging filter + multi-bit balancing, 128-bit response; ethanol at several concentrations and operating voltages; uniqueness 50.93%, randomness 97.92%, reliability 98.05%. Humidity not tested. No protocol, reading or calibration binding. Elements: D. | AI-suggested, confirm. Gas-sensor PUF (ASICON 2023) | W55: Primary synthesis | X55: PUF only
A56: S0420 | B56: 29 | C56: Zexin Ji, Xi Zhang, Zhanbo Chen, S S Wang, Wenbo Zhang, Hao Ye, X D Li | D56: 2026 | E56: Ni-Doped SnO2 Gas Sensor Array Enabled High-Randomness PUF for Hardware Security Applications | G56: https://doi.org/10.3390/mi17050597 | H56: Gas-sensor PUF (Ni-doped SnO2 array; 128-bit, random resistance balancing over sensor clusters) | I56: Device identity | J56: Node identity | K56: Y | L56: 1 | S56: =SUM(L56:R56) -> 1 | T56: Full text | U56: Implemented and evaluated | V56: Full text read (Micromachines 2026, 17(5), 597). Ethanol 500-600 ppm stimulus; entropy >0.99, uniqueness 49.8%, NIST pass; reliability >96% only under fixed laboratory conditions; humidity effects and ML modeling attacks not evaluated (future work). No reading, calibration or protocol binding. Elements: D. | AI-suggested, confirm. Gas-sensor PUF (Micromachines 2026) | W56: Primary synthesis | X56: PUF only
A58: Totals | L58: =SUM(L2:L56) -> 14 | M58: =SUM(M2:M56) -> 6 | N58: =SUM(N2:N56) -> 1 | O58: =SUM(O2:O56) -> 0 | P58: =SUM(P2:P56) -> 2 | Q58: =SUM(Q2:Q56) -> 3 | R58: =SUM(R2:R56) -> 7 | S58: =SUM(S2:S56) -> 33
A59: Max elements per study | S59: =MAX(S2:S56) -> 3
A60: Studies with chemical-sensor data | K60: =COUNTIF(K2:K56,"Y") -> 15
A61: Charted from abstract only | T61: =COUNTIF(T2:T56,"Abstract only") -> 23
A63: Evidence levels (Sec. III-C, V)
A64: Primary (full text) | B64: =COUNTIF(T2:T56,"Full text") -> 32 | C64: max elements | D64: =_xlfn.MAXIFS(S2:S56,T2:T56,"Full text") -> 3 | E64: studies coding calibration (C) | F64: =SUMIFS(O2:O56,T2:T56,"Full text") -> 0 | G64: with chemical-sensor data | H64: =COUNTIFS(K2:K56,"Y",T2:T56,"Full text") -> 11 | I64: TEE or enclave | J64: =COUNTIFS(X2:X56,"TEE or enclave",T2:T56,"Full text") -> 15 | K64: PUF only | L64: =COUNTIFS(X2:X56,"PUF only",T2:T56,"Full text") -> 8 | M64: Attestation without TEE | N64: =COUNTIFS(X2:X56,"Attestation without TEE",T2:T56,"Full text") -> 3 | O64: Cryptography only | P64: =COUNTIFS(X2:X56,"Cryptography only",T2:T56,"Full text") -> 2 | Q64: Breath or odor ML | R64: =COUNTIFS(X2:X56,"Breath or odor ML",T2:T56,"Full text") -> 2
A65: Supplementary (abstract only) | B65: =COUNTIF(T2:T56,"Abstract only") -> 23 | C65: max elements | D65: =_xlfn.MAXIFS(S2:S56,T2:T56,"Abstract only") -> 1 | E65: studies coding calibration (C) | F65: =SUMIFS(O2:O56,T2:T56,"Abstract only") -> 0 | G65: with chemical-sensor data | H65: =COUNTIFS(K2:K56,"Y",T2:T56,"Abstract only") -> 4 | I65: TEE or enclave | J65: =COUNTIFS(X2:X56,"TEE or enclave",T2:T56,"Abstract only") -> 13 | K65: PUF only | L65: =COUNTIFS(X2:X56,"PUF only",T2:T56,"Abstract only") -> 2 | M65: Attestation without TEE | N65: =COUNTIFS(X2:X56,"Attestation without TEE",T2:T56,"Abstract only") -> 3 | O65: Cryptography only | P65: =COUNTIFS(X2:X56,"Cryptography only",T2:T56,"Abstract only") -> 4 | Q65: Breath or odor ML | R65: =COUNTIFS(X2:X56,"Breath or odor ML",T2:T56,"Abstract only") -> 1

Sheet PRISMA counts
A1: PRISMA-ScR flow numbers
A2: Identification
A3: Records from databases (sum of Search log results) | B3: =SUM('Search log'!E2:E9) -> 429 | C3: From Search log.
A4: Records from other sources (web check, citation tracking) | B4: =COUNTIF(Screening!$B$2:$B$3001,"Other*") -> 6 | C4: Rows in Screening whose Source starts with "Other".
A5: Records loaded into Screening sheet | B5: =COUNTA(Screening!$A$2:$A$3001) -> 435 | C5: Should equal the two rows above.
A6: Check: loaded vs identified | B6: =IF(B5=0,"not loaded yet",IF(B5=B3+B4,"OK","MISMATCH")) -> OK | C6: MISMATCH means an export is missing or extra rows were added.
A7: Duplicates removed | B7: =COUNTIF(Screening!$I$2:$I$3001,"?*") -> 22 | C7: Rows with a Record ID in "Duplicate of".
A8: Screening
A9: Records screened (title/abstract) | B9: =B5-B7 -> 413
A10: Records excluded at title/abstract | B10: =COUNTIF(Screening!$J$2:$J$3001,"Exclude")-COUNTIFS(Screening!$J$2:$J$3001,"Exclude",Screening!$K$2:$K$3001,"E4") -> 341 | C10: Duplicates are counted above, not here.
A11: of which excluded by the narrower rule (E8) | B11: =COUNTIFS(Screening!$J$2:$J$3001,"Exclude",Screening!$K$2:$K$3001,"E8") -> 31 | C11: Reported as a protocol amendment in Section III.
A12: Records not yet screened | B12: =B9-COUNTIF(Screening!$J$2:$J$3001,"Include")-COUNTIF(Screening!$J$2:$J$3001,"Maybe")-B10 -> 0 | C12: Should reach 0 before reporting.
A13: Full texts sought (Include + Maybe at T/A) | B13: =COUNTIF(Screening!$J$2:$J$3001,"Include")+COUNTIF(Screening!$J$2:$J$3001,"Maybe") -> 72
A14: Full texts excluded, by reason
A15: E1 Off topic | B15: =COUNTIFS(Screening!$L$2:$L$3001,"Exclude",Screening!$M$2:$M$3001,"E1") -> 1
A16: E2 No technical evaluation | B16: =COUNTIFS(Screening!$L$2:$L$3001,"Exclude",Screening!$M$2:$M$3001,"E2") -> 5
A17: E3 Not English | B17: =COUNTIFS(Screening!$L$2:$L$3001,"Exclude",Screening!$M$2:$M$3001,"E3") -> 0
A18: E4 Duplicate/earlier version | B18: =COUNTIFS(Screening!$L$2:$L$3001,"Exclude",Screening!$M$2:$M$3001,"E4") -> 2
A19: E5 Full text unavailable | B19: =COUNTIFS(Screening!$L$2:$L$3001,"Exclude",Screening!$M$2:$M$3001,"E5") -> 0
A20: E6 Outside 2012–2026 | B20: =COUNTIFS(Screening!$L$2:$L$3001,"Exclude",Screening!$M$2:$M$3001,"E6") -> 0
A21: E7 Not peer-reviewed | B21: =COUNTIFS(Screening!$L$2:$L$3001,"Exclude",Screening!$M$2:$M$3001,"E7") -> 5
A22: E8 No sensor-data protection | B22: =COUNTIFS(Screening!$L$2:$L$3001,"Exclude",Screening!$M$2:$M$3001,"E8") -> 4
A23: Total excluded at full text | B23: =SUM(B15:B22) -> 17
A24: Included
A25: Studies included in review | B25: =COUNTIF(Screening!$L$2:$L$3001,"Include") -> 55
A26: of which charted from abstract only | B26: =COUNTIFS(Screening!$L$2:$L$3001,"Include",Screening!$R$2:$R$3001,"*abstract only*") -> 23 | C26: Full text unavailable; report this number in Section III.
A27: of which used chemical-sensor data | B27: =COUNTIFS(Screening!$L$2:$L$3001,"Include",Screening!$Q$2:$Q$3001,"Y") -> 15 | C27: Supports or limits the paper's gap claim.
A28: Check: sought = excluded + included | B28: =IF(COUNTA(Screening!$L$2:$L$3001)=0,"full-text review not started",IF(B13=B23+B25,"OK","in progress")) -> OK
A30: Full-text vs abstract assessment (matches Fig. 2)
A31: Reports assessed in full text | B31: =COUNTIFS(Screening!$L$2:$L$3001,"Include",Screening!$R$2:$R$3001,"*Full text read*")+COUNTIFS(Screening!$L$2:$L$3001,"Exclude",Screening!$R$2:$R$3001,"*Full text read*") -> 37 | C31: Notes column contains "Full text read".
A32: Reports assessed on abstract only (full text not retrieved) | B32: =COUNTIF(Screening!$L$2:$L$3001,"Include")+COUNTIF(Screening!$L$2:$L$3001,"Exclude")-B31 -> 35 | C32: Sought minus full text.
A33: Included studies charted from full text | B33: =COUNTIFS(Screening!$L$2:$L$3001,"Include",Screening!$R$2:$R$3001,"*Full text read*") -> 32
A34: Excluded at eligibility after full-text reading | B34: =COUNTIFS(Screening!$L$2:$L$3001,"Exclude",Screening!$R$2:$R$3001,"*Full text read*") -> 5
